{"type": "FeatureCollection", "features": [{"properties": {"ACCESSIBILITY_STATUS": "Not Accessible", "PARK_ID": "183", "AMENITY_SIZE": null, "STREET_NUMBER": "2106", "WIDTH": null, "LONGITUDE": -97.79210837, "YEAR_BUILT": null, "CREATED_BY": "hardya", "OTHER_PROTECTIONS": " ", "ZIP_CODE": "78745", "MODIFIED_BY": "hardya", "PRORAGIS_ID": "2584", "LENGTH": null, "RESERVATIONS": "No", "ASSET_MGMT_ID": 183.3001, "COUNTY": "Travis", "AMENITY_CLASS": 15, "CREATED_DATE": 1421232436000, "STATE": "TX", "SIZE_UNITS": null, "PROTECTION_COMMENTS": null, "AMENITY_TYPE": "Drinking Fountain", "AMENITYOWNER_TYPE": "Municipal", "INDOOR_OUTDOOR": "Outdoor", "MODIFIED_DATE": 1427200692000, "LWCF_PROTECTION": " ", "CITY_MUNICIPAL": "Austin", "LATITUDE": 30.22920351, "WIDTH_UNITS": null, "LENGTH_UNITS": null, "STREET_TYPE": "Trl.", "STREET_NAME": "Cimaron", "AMENITY_ID": "3001", "MANAGINGAGENCY_TYPE": "Municipal", "DESCRIPTION": "1 Human Spouts; 0 Dog Bowls; 0 Hose Bibs; Central Spout Type; Near Mixed Use Field", "OBJECTID": 60, "STATUS": "Open", "AMENITY_OWNER_NAME": "City of Austin Parks and Recreation", "YEAR_OPEN": null, "MANAGING_AGENCY_NAME": "City of Austin Parks and Recreation", "ADDRESS": "2106 Cimaron Trl., Austin, Texas 78745", "AMENITY_NAME": "Joslin Neighborhood Park Drinking Fountain"}, "type": "Feature", "geometry": {"type": "Point", "coordinates": [-97.7921083738611, 30.2292035089696]}, "id": 60}, {"properties": {"ACCESSIBILITY_STATUS": "Not Accessible", "PARK_ID": "183", "AMENITY_SIZE": null, "STREET_NUMBER": "2106", "WIDTH": null, "LONGITUDE": -97.79204187, "YEAR_BUILT": null, "CREATED_BY": "hardya", "OTHER_PROTECTIONS": " ", "ZIP_CODE": "78745", "MODIFIED_BY": "hardya", "PRORAGIS_ID": "8977", "LENGTH": null, "RESERVATIONS": "No", "ASSET_MGMT_ID": 183.4001, "COUNTY": "Travis", "AMENITY_CLASS": 17, "CREATED_DATE": 1425049915000, "STATE": "TX", "SIZE_UNITS": null, "PROTECTION_COMMENTS": null, "AMENITY_TYPE": "Picnic Table", "AMENITYOWNER_TYPE": "Municipal", "INDOOR_OUTDOOR": "Outdoor", "MODIFIED_DATE": 1427200700000, "LWCF_PROTECTION": " ", "CITY_MUNICIPAL": "Austin", "LATITUDE": 30.22914763, "WIDTH_UNITS": null, "LENGTH_UNITS": null, "STREET_TYPE": "Trl.", "STREET_NAME": "Cimaron", "AMENITY_ID": "4001", "MANAGINGAGENCY_TYPE": "Municipal", "DESCRIPTION": "Metal; No Concrete Pad", "OBJECTID": 771, "STATUS": "Open", "AMENITY_OWNER_NAME": "City of Austin Parks and Recreation", "YEAR_OPEN": null, "MANAGING_AGENCY_NAME": "City of Austin Parks and Recreation", "ADDRESS": "2106 Cimaron Trl., Austin, Texas 78745", "AMENITY_NAME": "Joslin Neighborhood Park: Mixed Use Field Picnic Table"}, "type": "Feature", "geometry": {"type": "Point", "coordinates": [-97.7920418653788, 30.2291476318381]}, "id": 771}, {"properties": {"ACCESSIBILITY_STATUS": "Not Accessible", "PARK_ID": "183", "AMENITY_SIZE": null, "STREET_NUMBER": "2106", "WIDTH": null, "LONGITUDE": -97.79212513, "YEAR_BUILT": null, "CREATED_BY": "hardya", "OTHER_PROTECTIONS": " ", "ZIP_CODE": "78745", "MODIFIED_BY": "hardya", "PRORAGIS_ID": "8978", "LENGTH": null, "RESERVATIONS": "No", "ASSET_MGMT_ID": 183.4002, "COUNTY": "Travis", "AMENITY_CLASS": 17, "CREATED_DATE": 1425050166000, "STATE": "TX", "SIZE_UNITS": null, "PROTECTION_COMMENTS": null, "AMENITY_TYPE": "Picnic Table", "AMENITYOWNER_TYPE": "Municipal", "INDOOR_OUTDOOR": "Outdoor", "MODIFIED_DATE": 1427200700000, "LWCF_PROTECTION": " ", "CITY_MUNICIPAL": "Austin", "LATITUDE": 30.22861041, "WIDTH_UNITS": null, "LENGTH_UNITS": null, "STREET_TYPE": "Trl.", "STREET_NAME": "Cimaron", "AMENITY_ID": "4002", "MANAGINGAGENCY_TYPE": "Municipal", "DESCRIPTION": "Metal; No Concrete Pad", "OBJECTID": 1746, "STATUS": "Open", "AMENITY_OWNER_NAME": "City of Austin Parks and Recreation", "YEAR_OPEN": null, "MANAGING_AGENCY_NAME": "City of Austin Parks and Recreation", "ADDRESS": "2106 Cimaron Trl., Austin, Texas 78745", "AMENITY_NAME": "Joslin Neighborhood Park Picnic Table"}, "type": "Feature", "geometry": {"type": "Point", "coordinates": [-97.7921251306137, 30.2286104091695]}, "id": 1746}]}