{"features": [{"geometry": {"coordinates": [-97.7733723295116, 30.3208489563321], "type": "Point"}, "id": 1058, "properties": {"WIDTH_UNITS": null, "LENGTH": null, "MODIFIED_DATE": 1427200700000, "DESCRIPTION": "Concrete; On Concrete Pad", "AMENITY_ID": "4002", "PRORAGIS_ID": "10244", "YEAR_BUILT": null, "STREET_NUMBER": "3800", "STATUS": "Open", "LWCF_PROTECTION": " ", "AMENITY_OWNER_NAME": "City of Austin Parks and Recreation", "INDOOR_OUTDOOR": "Outdoor", "CREATED_BY": "hardya", "CITY_MUNICIPAL": "Austin", "PROTECTION_COMMENTS": null, "YEAR_OPEN": null, "STREET_NAME": "Mount Bonnell", "AMENITY_NAME": "Covert Park at Mount Bonnell Picnic Table 2", "LONGITUDE": -97.77337233, "MANAGING_AGENCY_NAME": "City of Austin Parks and Recreation", "SIZE_UNITS": null, "LENGTH_UNITS": null, "STATE": "TX", "AMENITYOWNER_TYPE": "Municipal", "ADDRESS": "3800 Mount Bonnell Rd., Austin, Texas 78731", "RESERVATIONS": "No", "ZIP_CODE": "78731", "PARK_ID": "213", "COUNTY": "Travis", "MODIFIED_BY": "hardya", "OTHER_PROTECTIONS": " ", "AMENITY_CLASS": 17, "OBJECTID": 1058, "STREET_TYPE": "Rd.", "CREATED_DATE": 1426497441000, "LATITUDE": 30.32084896, "WIDTH": null, "AMENITY_TYPE": "Picnic Table", "MANAGINGAGENCY_TYPE": "Municipal", "AMENITY_SIZE": null, "ASSET_MGMT_ID": 213.4002, "ACCESSIBILITY_STATUS": "Not Accessible"}, "type": "Feature"}, {"geometry": {"coordinates": [-97.7736013865502, 30.323717999676], "type": "Point"}, "id": 1630, "properties": {"WIDTH_UNITS": null, "LENGTH": null, "MODIFIED_DATE": 1427200700000, "DESCRIPTION": "Concrete; On Concrete Pad", "AMENITY_ID": "4003", "PRORAGIS_ID": "10245", "YEAR_BUILT": null, "STREET_NUMBER": "3800", "STATUS": "Open", "LWCF_PROTECTION": " ", "AMENITY_OWNER_NAME": "City of Austin Parks and Recreation", "INDOOR_OUTDOOR": "Outdoor", "CREATED_BY": "hardya", "CITY_MUNICIPAL": "Austin", "PROTECTION_COMMENTS": null, "YEAR_OPEN": null, "STREET_NAME": "Mount Bonnell", "AMENITY_NAME": "Covert Park at Mount Bonnell Picnic Table 3", "LONGITUDE": -97.77360139, "MANAGING_AGENCY_NAME": "City of Austin Parks and Recreation", "SIZE_UNITS": null, "LENGTH_UNITS": null, "STATE": "TX", "AMENITYOWNER_TYPE": "Municipal", "ADDRESS": "3800 Mount Bonnell Rd., Austin, Texas 78731", "RESERVATIONS": "No", "ZIP_CODE": "78731", "PARK_ID": "213", "COUNTY": "Travis", "MODIFIED_BY": "hardya", "OTHER_PROTECTIONS": " ", "AMENITY_CLASS": 17, "OBJECTID": 1630, "STREET_TYPE": "Rd.", "CREATED_DATE": 1426498047000, "LATITUDE": 30.323718, "WIDTH": null, "AMENITY_TYPE": "Picnic Table", "MANAGINGAGENCY_TYPE": "Municipal", "AMENITY_SIZE": null, "ASSET_MGMT_ID": 213.4003, "ACCESSIBILITY_STATUS": "Not Accessible"}, "type": "Feature"}, {"geometry": {"coordinates": [-97.773535625848, 30.3207654435801], "type": "Point"}, "id": 1742, "properties": {"WIDTH_UNITS": null, "LENGTH": null, "MODIFIED_DATE": 1427200700000, "DESCRIPTION": "Concrete; On Concrete Pad", "AMENITY_ID": "4001", "PRORAGIS_ID": "10243", "YEAR_BUILT": null, "STREET_NUMBER": "3800", "STATUS": "Open", "LWCF_PROTECTION": " ", "AMENITY_OWNER_NAME": "City of Austin Parks and Recreation", "INDOOR_OUTDOOR": "Outdoor", "CREATED_BY": "hardya", "CITY_MUNICIPAL": "Austin", "PROTECTION_COMMENTS": null, "YEAR_OPEN": null, "STREET_NAME": "Mount Bonnell", "AMENITY_NAME": "Covert Park at Mount Bonnell Picnic Table 1", "LONGITUDE": -97.77353563, "MANAGING_AGENCY_NAME": "City of Austin Parks and Recreation", "SIZE_UNITS": null, "LENGTH_UNITS": null, "STATE": "TX", "AMENITYOWNER_TYPE": "Municipal", "ADDRESS": "3800 Mount Bonnell Rd., Austin, Texas 78731", "RESERVATIONS": "No", "ZIP_CODE": "78731", "PARK_ID": "213", "COUNTY": "Travis", "MODIFIED_BY": "hardya", "OTHER_PROTECTIONS": " ", "AMENITY_CLASS": 17, "OBJECTID": 1742, "STREET_TYPE": "Rd.", "CREATED_DATE": 1426497431000, "LATITUDE": 30.32076544, "WIDTH": null, "AMENITY_TYPE": "Picnic Table", "MANAGINGAGENCY_TYPE": "Municipal", "AMENITY_SIZE": null, "ASSET_MGMT_ID": 213.4001, "ACCESSIBILITY_STATUS": "Not Accessible"}, "type": "Feature"}], "type": "FeatureCollection"}