{"features": [{"geometry": {"coordinates": [-97.7207065746873, 30.3277990666507], "type": "Point"}, "id": 883, "properties": {"WIDTH_UNITS": null, "LENGTH": null, "MODIFIED_DATE": 1427200699000, "DESCRIPTION": "1 Human Spouts; 0 Dog Bowl; 0 Hose Bibs; Central Spout Type; Next to Pavilion", "AMENITY_ID": "3001", "PRORAGIS_ID": "2881", "YEAR_BUILT": null, "STREET_NUMBER": "405", "STATUS": "Open", "LWCF_PROTECTION": " ", "AMENITY_OWNER_NAME": "Austin Independent School District", "INDOOR_OUTDOOR": "Outdoor", "CREATED_BY": "hardya", "CITY_MUNICIPAL": "Austin", "PROTECTION_COMMENTS": null, "YEAR_OPEN": null, "STREET_NAME": "Denson", "AMENITY_NAME": "Reilly School Park Drinking Fountain", "LONGITUDE": -97.72070658, "MANAGING_AGENCY_NAME": "City of Austin Parks and Recreation", "SIZE_UNITS": null, "LENGTH_UNITS": null, "STATE": "TX", "AMENITYOWNER_TYPE": "School", "ADDRESS": "405 Denson Dr., Austin, Texas 78752", "RESERVATIONS": "No", "ZIP_CODE": "78752", "PARK_ID": "254", "COUNTY": "Travis", "MODIFIED_BY": "hardya", "OTHER_PROTECTIONS": " ", "AMENITY_CLASS": 15, "OBJECTID": 883, "STREET_TYPE": "Dr.", "CREATED_DATE": 1421314417000, "LATITUDE": 30.32779907, "WIDTH": null, "AMENITY_TYPE": "Drinking Fountain", "MANAGINGAGENCY_TYPE": "Municipal", "AMENITY_SIZE": null, "ASSET_MGMT_ID": 254.3001, "ACCESSIBILITY_STATUS": "Not Accessible"}, "type": "Feature"}], "type": "FeatureCollection"}