{"type": "FeatureCollection", "features": [{"properties": {"ACCESSIBILITY_STATUS": "Not Accessible", "PARK_ID": "198", "AMENITY_SIZE": null, "STREET_NUMBER": "1180", "WIDTH": null, "LONGITUDE": -97.730065, "YEAR_BUILT": null, "CREATED_BY": "hardya", "OTHER_PROTECTIONS": " ", "ZIP_CODE": "78702", "MODIFIED_BY": "hardya", "PRORAGIS_ID": "523", "LENGTH": null, "RESERVATIONS": "No", "ASSET_MGMT_ID": 198.4001, "COUNTY": "Travis", "AMENITY_CLASS": 17, "CREATED_DATE": 1407153796000, "STATE": "TX", "SIZE_UNITS": null, "PROTECTION_COMMENTS": null, "AMENITY_TYPE": "Bench", "AMENITYOWNER_TYPE": "Municipal", "INDOOR_OUTDOOR": "Outdoor", "MODIFIED_DATE": 1427200692000, "LWCF_PROTECTION": " ", "CITY_MUNICIPAL": "Austin", "LATITUDE": 30.27128967, "WIDTH_UNITS": null, "LENGTH_UNITS": null, "STREET_TYPE": "St.", "STREET_NAME": "Curve", "AMENITY_ID": "4001", "MANAGINGAGENCY_TYPE": "Municipal", "DESCRIPTION": "1 Wood Bench", "OBJECTID": 396, "STATUS": "Open", "AMENITY_OWNER_NAME": "City of Austin Parks and Recreation", "YEAR_OPEN": null, "MANAGING_AGENCY_NAME": "City of Austin Parks and Recreation", "ADDRESS": "1180 Curve St., Austin, Texas 78702", "AMENITY_NAME": "Lott Pocket Park Bench"}, "type": "Feature", "geometry": {"type": "Point", "coordinates": [-97.7300649955557, 30.2712896738271]}, "id": 396}, {"properties": {"ACCESSIBILITY_STATUS": "Accessible", "PARK_ID": "198", "AMENITY_SIZE": null, "STREET_NUMBER": "1180", "WIDTH": null, "LONGITUDE": -97.72994607, "YEAR_BUILT": null, "CREATED_BY": "hardya", "OTHER_PROTECTIONS": " ", "ZIP_CODE": "78702", "MODIFIED_BY": "hardya", "PRORAGIS_ID": "2601", "LENGTH": null, "RESERVATIONS": "No", "ASSET_MGMT_ID": 198.3003, "COUNTY": "Travis", "AMENITY_CLASS": 15, "CREATED_DATE": 1421236731000, "STATE": "TX", "SIZE_UNITS": null, "PROTECTION_COMMENTS": null, "AMENITY_TYPE": "Drinking Fountain", "AMENITYOWNER_TYPE": "Municipal", "INDOOR_OUTDOOR": "Outdoor", "MODIFIED_DATE": 1427200699000, "LWCF_PROTECTION": " ", "CITY_MUNICIPAL": "Austin", "LATITUDE": 30.27104622, "WIDTH_UNITS": null, "LENGTH_UNITS": null, "STREET_TYPE": "St.", "STREET_NAME": "Curve", "AMENITY_ID": "3003", "MANAGINGAGENCY_TYPE": "Municipal", "DESCRIPTION": "3 Human Spouts; 0 Dog Bowls; 0 Hose Bibs; Unknown Spout Type; Near Sprayground", "OBJECTID": 462, "STATUS": "Open", "AMENITY_OWNER_NAME": "City of Austin Parks and Recreation", "YEAR_OPEN": null, "MANAGING_AGENCY_NAME": "City of Austin Parks and Recreation", "ADDRESS": "1180 Curve St., Austin, Texas 78702", "AMENITY_NAME": "Lott Pocket Park Drinking Fountain"}, "type": "Feature", "geometry": {"type": "Point", "coordinates": [-97.729946071173, 30.2710462208505]}, "id": 462}, {"properties": {"ACCESSIBILITY_STATUS": "Accessible", "PARK_ID": "198", "AMENITY_SIZE": null, "STREET_NUMBER": "1180", "WIDTH": null, "LONGITUDE": -97.73006195, "YEAR_BUILT": null, "CREATED_BY": "hardya", "OTHER_PROTECTIONS": " ", "ZIP_CODE": "78702", "MODIFIED_BY": "hardya", "PRORAGIS_ID": "9309", "LENGTH": null, "RESERVATIONS": "No", "ASSET_MGMT_ID": 198.4002, "COUNTY": "Travis", "AMENITY_CLASS": 17, "CREATED_DATE": 1425299155000, "STATE": "TX", "SIZE_UNITS": null, "PROTECTION_COMMENTS": null, "AMENITY_TYPE": "Picnic Table", "AMENITYOWNER_TYPE": "Municipal", "INDOOR_OUTDOOR": "Outdoor", "MODIFIED_DATE": 1427200700000, "LWCF_PROTECTION": " ", "CITY_MUNICIPAL": "Austin", "LATITUDE": 30.2710047, "WIDTH_UNITS": null, "LENGTH_UNITS": null, "STREET_TYPE": "St.", "STREET_NAME": "Curve", "AMENITY_ID": "4002", "MANAGINGAGENCY_TYPE": "Municipal", "DESCRIPTION": "Metal; On Concrete Pad", "OBJECTID": 1437, "STATUS": "Open", "AMENITY_OWNER_NAME": "City of Austin Parks and Recreation", "YEAR_OPEN": null, "MANAGING_AGENCY_NAME": "City of Austin Parks and Recreation", "ADDRESS": "1180 Curve St., Austin, Texas 78702", "AMENITY_NAME": "Lott Pocket Park Picnic Table"}, "type": "Feature", "geometry": {"type": "Point", "coordinates": [-97.7300619464074, 30.2710047049276]}, "id": 1437}]}