{"features": [{"id": 883, "geometry": {"coordinates": [-97.7207065746873, 30.3277990666507], "type": "Point"}, "type": "Feature", "properties": {"YEAR_BUILT": null, "ZIP_CODE": "78752", "PRORAGIS_ID": "2881", "PROTECTION_COMMENTS": null, "COUNTY": "Travis", "RESERVATIONS": "No", "LENGTH": null, "OBJECTID": 883, "PARK_ID": "254", "MODIFIED_BY": "hardya", "AMENITY_OWNER_NAME": "Austin Independent School District", "YEAR_OPEN": null, "AMENITYOWNER_TYPE": "School", "INDOOR_OUTDOOR": "Outdoor", "OTHER_PROTECTIONS": " ", "ACCESSIBILITY_STATUS": "Not Accessible", "WIDTH": null, "STREET_NUMBER": "405", "AMENITY_SIZE": null, "WIDTH_UNITS": null, "LONGITUDE": -97.72070658, "CREATED_DATE": 1421314417000, "AMENITY_NAME": "Reilly School Park Drinking Fountain", "ASSET_MGMT_ID": 254.3001, "CREATED_BY": "hardya", "STATUS": "Open", "CITY_MUNICIPAL": "Austin", "MODIFIED_DATE": 1427200699000, "MANAGINGAGENCY_TYPE": "Municipal", "STREET_TYPE": "Dr.", "MANAGING_AGENCY_NAME": "City of Austin Parks and Recreation", "AMENITY_CLASS": 15, "SIZE_UNITS": null, "LWCF_PROTECTION": " ", "STREET_NAME": "Denson", "DESCRIPTION": "1 Human Spouts; 0 Dog Bowl; 0 Hose Bibs; Central Spout Type; Next to Pavilion", "AMENITY_ID": "3001", "ADDRESS": "405 Denson Dr., Austin, Texas 78752", "LATITUDE": 30.32779907, "STATE": "TX", "LENGTH_UNITS": null, "AMENITY_TYPE": "Drinking Fountain"}}], "type": "FeatureCollection"}