{"features": [{"id": 396, "geometry": {"coordinates": [-97.7300649955557, 30.2712896738271], "type": "Point"}, "type": "Feature", "properties": {"YEAR_BUILT": null, "ZIP_CODE": "78702", "PRORAGIS_ID": "523", "PROTECTION_COMMENTS": null, "COUNTY": "Travis", "RESERVATIONS": "No", "LENGTH": null, "OBJECTID": 396, "PARK_ID": "198", "MODIFIED_BY": "hardya", "AMENITY_OWNER_NAME": "City of Austin Parks and Recreation", "YEAR_OPEN": null, "AMENITYOWNER_TYPE": "Municipal", "INDOOR_OUTDOOR": "Outdoor", "OTHER_PROTECTIONS": " ", "ACCESSIBILITY_STATUS": "Not Accessible", "WIDTH": null, "STREET_NUMBER": "1180", "AMENITY_SIZE": null, "WIDTH_UNITS": null, "LONGITUDE": -97.730065, "CREATED_DATE": 1407153796000, "AMENITY_NAME": "Lott Pocket Park Bench", "ASSET_MGMT_ID": 198.4001, "CREATED_BY": "hardya", "STATUS": "Open", "CITY_MUNICIPAL": "Austin", "MODIFIED_DATE": 1427200692000, "MANAGINGAGENCY_TYPE": "Municipal", "STREET_TYPE": "St.", "MANAGING_AGENCY_NAME": "City of Austin Parks and Recreation", "AMENITY_CLASS": 17, "SIZE_UNITS": null, "LWCF_PROTECTION": " ", "STREET_NAME": "Curve", "DESCRIPTION": "1 Wood Bench", "AMENITY_ID": "4001", "ADDRESS": "1180 Curve St., Austin, Texas 78702", "LATITUDE": 30.27128967, "STATE": "TX", "LENGTH_UNITS": null, "AMENITY_TYPE": "Bench"}}, {"id": 462, "geometry": {"coordinates": [-97.729946071173, 30.2710462208505], "type": "Point"}, "type": "Feature", "properties": {"YEAR_BUILT": null, "ZIP_CODE": "78702", "PRORAGIS_ID": "2601", "PROTECTION_COMMENTS": null, "COUNTY": "Travis", "RESERVATIONS": "No", "LENGTH": null, "OBJECTID": 462, "PARK_ID": "198", "MODIFIED_BY": "hardya", "AMENITY_OWNER_NAME": "City of Austin Parks and Recreation", "YEAR_OPEN": null, "AMENITYOWNER_TYPE": "Municipal", "INDOOR_OUTDOOR": "Outdoor", "OTHER_PROTECTIONS": " ", "ACCESSIBILITY_STATUS": "Accessible", "WIDTH": null, "STREET_NUMBER": "1180", "AMENITY_SIZE": null, "WIDTH_UNITS": null, "LONGITUDE": -97.72994607, "CREATED_DATE": 1421236731000, "AMENITY_NAME": "Lott Pocket Park Drinking Fountain", "ASSET_MGMT_ID": 198.3003, "CREATED_BY": "hardya", "STATUS": "Open", "CITY_MUNICIPAL": "Austin", "MODIFIED_DATE": 1427200699000, "MANAGINGAGENCY_TYPE": "Municipal", "STREET_TYPE": "St.", "MANAGING_AGENCY_NAME": "City of Austin Parks and Recreation", "AMENITY_CLASS": 15, "SIZE_UNITS": null, "LWCF_PROTECTION": " ", "STREET_NAME": "Curve", "DESCRIPTION": "3 Human Spouts; 0 Dog Bowls; 0 Hose Bibs; Unknown Spout Type; Near Sprayground", "AMENITY_ID": "3003", "ADDRESS": "1180 Curve St., Austin, Texas 78702", "LATITUDE": 30.27104622, "STATE": "TX", "LENGTH_UNITS": null, "AMENITY_TYPE": "Drinking Fountain"}}, {"id": 1437, "geometry": {"coordinates": [-97.7300619464074, 30.2710047049276], "type": "Point"}, "type": "Feature", "properties": {"YEAR_BUILT": null, "ZIP_CODE": "78702", "PRORAGIS_ID": "9309", "PROTECTION_COMMENTS": null, "COUNTY": "Travis", "RESERVATIONS": "No", "LENGTH": null, "OBJECTID": 1437, "PARK_ID": "198", "MODIFIED_BY": "hardya", "AMENITY_OWNER_NAME": "City of Austin Parks and Recreation", "YEAR_OPEN": null, "AMENITYOWNER_TYPE": "Municipal", "INDOOR_OUTDOOR": "Outdoor", "OTHER_PROTECTIONS": " ", "ACCESSIBILITY_STATUS": "Accessible", "WIDTH": null, "STREET_NUMBER": "1180", "AMENITY_SIZE": null, "WIDTH_UNITS": null, "LONGITUDE": -97.73006195, "CREATED_DATE": 1425299155000, "AMENITY_NAME": "Lott Pocket Park Picnic Table", "ASSET_MGMT_ID": 198.4002, "CREATED_BY": "hardya", "STATUS": "Open", "CITY_MUNICIPAL": "Austin", "MODIFIED_DATE": 1427200700000, "MANAGINGAGENCY_TYPE": "Municipal", "STREET_TYPE": "St.", "MANAGING_AGENCY_NAME": "City of Austin Parks and Recreation", "AMENITY_CLASS": 17, "SIZE_UNITS": null, "LWCF_PROTECTION": " ", "STREET_NAME": "Curve", "DESCRIPTION": "Metal; On Concrete Pad", "AMENITY_ID": "4002", "ADDRESS": "1180 Curve St., Austin, Texas 78702", "LATITUDE": 30.2710047, "STATE": "TX", "LENGTH_UNITS": null, "AMENITY_TYPE": "Picnic Table"}}], "type": "FeatureCollection"}