{"features": [{"id": 1058, "geometry": {"coordinates": [-97.7733723295116, 30.3208489563321], "type": "Point"}, "type": "Feature", "properties": {"YEAR_BUILT": null, "ZIP_CODE": "78731", "PRORAGIS_ID": "10244", "PROTECTION_COMMENTS": null, "COUNTY": "Travis", "RESERVATIONS": "No", "LENGTH": null, "OBJECTID": 1058, "PARK_ID": "213", "MODIFIED_BY": "hardya", "AMENITY_OWNER_NAME": "City of Austin Parks and Recreation", "YEAR_OPEN": null, "AMENITYOWNER_TYPE": "Municipal", "INDOOR_OUTDOOR": "Outdoor", "OTHER_PROTECTIONS": " ", "ACCESSIBILITY_STATUS": "Not Accessible", "WIDTH": null, "STREET_NUMBER": "3800", "AMENITY_SIZE": null, "WIDTH_UNITS": null, "LONGITUDE": -97.77337233, "CREATED_DATE": 1426497441000, "AMENITY_NAME": "Covert Park at Mount Bonnell Picnic Table 2", "ASSET_MGMT_ID": 213.4002, "CREATED_BY": "hardya", "STATUS": "Open", "CITY_MUNICIPAL": "Austin", "MODIFIED_DATE": 1427200700000, "MANAGINGAGENCY_TYPE": "Municipal", "STREET_TYPE": "Rd.", "MANAGING_AGENCY_NAME": "City of Austin Parks and Recreation", "AMENITY_CLASS": 17, "SIZE_UNITS": null, "LWCF_PROTECTION": " ", "STREET_NAME": "Mount Bonnell", "DESCRIPTION": "Concrete; On Concrete Pad", "AMENITY_ID": "4002", "ADDRESS": "3800 Mount Bonnell Rd., Austin, Texas 78731", "LATITUDE": 30.32084896, "STATE": "TX", "LENGTH_UNITS": null, "AMENITY_TYPE": "Picnic Table"}}, {"id": 1630, "geometry": {"coordinates": [-97.7736013865502, 30.323717999676], "type": "Point"}, "type": "Feature", "properties": {"YEAR_BUILT": null, "ZIP_CODE": "78731", "PRORAGIS_ID": "10245", "PROTECTION_COMMENTS": null, "COUNTY": "Travis", "RESERVATIONS": "No", "LENGTH": null, "OBJECTID": 1630, "PARK_ID": "213", "MODIFIED_BY": "hardya", "AMENITY_OWNER_NAME": "City of Austin Parks and Recreation", "YEAR_OPEN": null, "AMENITYOWNER_TYPE": "Municipal", "INDOOR_OUTDOOR": "Outdoor", "OTHER_PROTECTIONS": " ", "ACCESSIBILITY_STATUS": "Not Accessible", "WIDTH": null, "STREET_NUMBER": "3800", "AMENITY_SIZE": null, "WIDTH_UNITS": null, "LONGITUDE": -97.77360139, "CREATED_DATE": 1426498047000, "AMENITY_NAME": "Covert Park at Mount Bonnell Picnic Table 3", "ASSET_MGMT_ID": 213.4003, "CREATED_BY": "hardya", "STATUS": "Open", "CITY_MUNICIPAL": "Austin", "MODIFIED_DATE": 1427200700000, "MANAGINGAGENCY_TYPE": "Municipal", "STREET_TYPE": "Rd.", "MANAGING_AGENCY_NAME": "City of Austin Parks and Recreation", "AMENITY_CLASS": 17, "SIZE_UNITS": null, "LWCF_PROTECTION": " ", "STREET_NAME": "Mount Bonnell", "DESCRIPTION": "Concrete; On Concrete Pad", "AMENITY_ID": "4003", "ADDRESS": "3800 Mount Bonnell Rd., Austin, Texas 78731", "LATITUDE": 30.323718, "STATE": "TX", "LENGTH_UNITS": null, "AMENITY_TYPE": "Picnic Table"}}, {"id": 1742, "geometry": {"coordinates": [-97.773535625848, 30.3207654435801], "type": "Point"}, "type": "Feature", "properties": {"YEAR_BUILT": null, "ZIP_CODE": "78731", "PRORAGIS_ID": "10243", "PROTECTION_COMMENTS": null, "COUNTY": "Travis", "RESERVATIONS": "No", "LENGTH": null, "OBJECTID": 1742, "PARK_ID": "213", "MODIFIED_BY": "hardya", "AMENITY_OWNER_NAME": "City of Austin Parks and Recreation", "YEAR_OPEN": null, "AMENITYOWNER_TYPE": "Municipal", "INDOOR_OUTDOOR": "Outdoor", "OTHER_PROTECTIONS": " ", "ACCESSIBILITY_STATUS": "Not Accessible", "WIDTH": null, "STREET_NUMBER": "3800", "AMENITY_SIZE": null, "WIDTH_UNITS": null, "LONGITUDE": -97.77353563, "CREATED_DATE": 1426497431000, "AMENITY_NAME": "Covert Park at Mount Bonnell Picnic Table 1", "ASSET_MGMT_ID": 213.4001, "CREATED_BY": "hardya", "STATUS": "Open", "CITY_MUNICIPAL": "Austin", "MODIFIED_DATE": 1427200700000, "MANAGINGAGENCY_TYPE": "Municipal", "STREET_TYPE": "Rd.", "MANAGING_AGENCY_NAME": "City of Austin Parks and Recreation", "AMENITY_CLASS": 17, "SIZE_UNITS": null, "LWCF_PROTECTION": " ", "STREET_NAME": "Mount Bonnell", "DESCRIPTION": "Concrete; On Concrete Pad", "AMENITY_ID": "4001", "ADDRESS": "3800 Mount Bonnell Rd., Austin, Texas 78731", "LATITUDE": 30.32076544, "STATE": "TX", "LENGTH_UNITS": null, "AMENITY_TYPE": "Picnic Table"}}], "type": "FeatureCollection"}