{"features": [{"geometry": {"coordinates": [-97.7921083738611, 30.2292035089696], "type": "Point"}, "id": 60, "properties": {"WIDTH_UNITS": null, "LENGTH": null, "MODIFIED_DATE": 1427200692000, "DESCRIPTION": "1 Human Spouts; 0 Dog Bowls; 0 Hose Bibs; Central Spout Type; Near Mixed Use Field", "AMENITY_ID": "3001", "PRORAGIS_ID": "2584", "YEAR_BUILT": null, "STREET_NUMBER": "2106", "STATUS": "Open", "LWCF_PROTECTION": " ", "AMENITY_OWNER_NAME": "City of Austin Parks and Recreation", "INDOOR_OUTDOOR": "Outdoor", "CREATED_BY": "hardya", "CITY_MUNICIPAL": "Austin", "PROTECTION_COMMENTS": null, "YEAR_OPEN": null, "STREET_NAME": "Cimaron", "AMENITY_NAME": "Joslin Neighborhood Park Drinking Fountain", "LONGITUDE": -97.79210837, "MANAGING_AGENCY_NAME": "City of Austin Parks and Recreation", "SIZE_UNITS": null, "LENGTH_UNITS": null, "STATE": "TX", "AMENITYOWNER_TYPE": "Municipal", "ADDRESS": "2106 Cimaron Trl., Austin, Texas 78745", "RESERVATIONS": "No", "ZIP_CODE": "78745", "PARK_ID": "183", "COUNTY": "Travis", "MODIFIED_BY": "hardya", "OTHER_PROTECTIONS": " ", "AMENITY_CLASS": 15, "OBJECTID": 60, "STREET_TYPE": "Trl.", "CREATED_DATE": 1421232436000, "LATITUDE": 30.22920351, "WIDTH": null, "AMENITY_TYPE": "Drinking Fountain", "MANAGINGAGENCY_TYPE": "Municipal", "AMENITY_SIZE": null, "ASSET_MGMT_ID": 183.3001, "ACCESSIBILITY_STATUS": "Not Accessible"}, "type": "Feature"}, {"geometry": {"coordinates": [-97.7920418653788, 30.2291476318381], "type": "Point"}, "id": 771, "properties": {"WIDTH_UNITS": null, "LENGTH": null, "MODIFIED_DATE": 1427200700000, "DESCRIPTION": "Metal; No Concrete Pad", "AMENITY_ID": "4001", "PRORAGIS_ID": "8977", "YEAR_BUILT": null, "STREET_NUMBER": "2106", "STATUS": "Open", "LWCF_PROTECTION": " ", "AMENITY_OWNER_NAME": "City of Austin Parks and Recreation", "INDOOR_OUTDOOR": "Outdoor", "CREATED_BY": "hardya", "CITY_MUNICIPAL": "Austin", "PROTECTION_COMMENTS": null, "YEAR_OPEN": null, "STREET_NAME": "Cimaron", "AMENITY_NAME": "Joslin Neighborhood Park: Mixed Use Field Picnic Table", "LONGITUDE": -97.79204187, "MANAGING_AGENCY_NAME": "City of Austin Parks and Recreation", "SIZE_UNITS": null, "LENGTH_UNITS": null, "STATE": "TX", "AMENITYOWNER_TYPE": "Municipal", "ADDRESS": "2106 Cimaron Trl., Austin, Texas 78745", "RESERVATIONS": "No", "ZIP_CODE": "78745", "PARK_ID": "183", "COUNTY": "Travis", "MODIFIED_BY": "hardya", "OTHER_PROTECTIONS": " ", "AMENITY_CLASS": 17, "OBJECTID": 771, "STREET_TYPE": "Trl.", "CREATED_DATE": 1425049915000, "LATITUDE": 30.22914763, "WIDTH": null, "AMENITY_TYPE": "Picnic Table", "MANAGINGAGENCY_TYPE": "Municipal", "AMENITY_SIZE": null, "ASSET_MGMT_ID": 183.4001, "ACCESSIBILITY_STATUS": "Not Accessible"}, "type": "Feature"}, {"geometry": {"coordinates": [-97.7921251306137, 30.2286104091695], "type": "Point"}, "id": 1746, "properties": {"WIDTH_UNITS": null, "LENGTH": null, "MODIFIED_DATE": 1427200700000, "DESCRIPTION": "Metal; No Concrete Pad", "AMENITY_ID": "4002", "PRORAGIS_ID": "8978", "YEAR_BUILT": null, "STREET_NUMBER": "2106", "STATUS": "Open", "LWCF_PROTECTION": " ", "AMENITY_OWNER_NAME": "City of Austin Parks and Recreation", "INDOOR_OUTDOOR": "Outdoor", "CREATED_BY": "hardya", "CITY_MUNICIPAL": "Austin", "PROTECTION_COMMENTS": null, "YEAR_OPEN": null, "STREET_NAME": "Cimaron", "AMENITY_NAME": "Joslin Neighborhood Park Picnic Table", "LONGITUDE": -97.79212513, "MANAGING_AGENCY_NAME": "City of Austin Parks and Recreation", "SIZE_UNITS": null, "LENGTH_UNITS": null, "STATE": "TX", "AMENITYOWNER_TYPE": "Municipal", "ADDRESS": "2106 Cimaron Trl., Austin, Texas 78745", "RESERVATIONS": "No", "ZIP_CODE": "78745", "PARK_ID": "183", "COUNTY": "Travis", "MODIFIED_BY": "hardya", "OTHER_PROTECTIONS": " ", "AMENITY_CLASS": 17, "OBJECTID": 1746, "STREET_TYPE": "Trl.", "CREATED_DATE": 1425050166000, "LATITUDE": 30.22861041, "WIDTH": null, "AMENITY_TYPE": "Picnic Table", "MANAGINGAGENCY_TYPE": "Municipal", "AMENITY_SIZE": null, "ASSET_MGMT_ID": 183.4002, "ACCESSIBILITY_STATUS": "Not Accessible"}, "type": "Feature"}], "type": "FeatureCollection"}