{"type": "FeatureCollection", "features": [{"properties": {"ACCESSIBILITY_STATUS": "Not Accessible", "PARK_ID": "213", "AMENITY_SIZE": null, "STREET_NUMBER": "3800", "WIDTH": null, "LONGITUDE": -97.77337233, "YEAR_BUILT": null, "CREATED_BY": "hardya", "OTHER_PROTECTIONS": " ", "ZIP_CODE": "78731", "MODIFIED_BY": "hardya", "PRORAGIS_ID": "10244", "LENGTH": null, "RESERVATIONS": "No", "ASSET_MGMT_ID": 213.4002, "COUNTY": "Travis", "AMENITY_CLASS": 17, "CREATED_DATE": 1426497441000, "STATE": "TX", "SIZE_UNITS": null, "PROTECTION_COMMENTS": null, "AMENITY_TYPE": "Picnic Table", "AMENITYOWNER_TYPE": "Municipal", "INDOOR_OUTDOOR": "Outdoor", "MODIFIED_DATE": 1427200700000, "LWCF_PROTECTION": " ", "CITY_MUNICIPAL": "Austin", "LATITUDE": 30.32084896, "WIDTH_UNITS": null, "LENGTH_UNITS": null, "STREET_TYPE": "Rd.", "STREET_NAME": "Mount Bonnell", "AMENITY_ID": "4002", "MANAGINGAGENCY_TYPE": "Municipal", "DESCRIPTION": "Concrete; On Concrete Pad", "OBJECTID": 1058, "STATUS": "Open", "AMENITY_OWNER_NAME": "City of Austin Parks and Recreation", "YEAR_OPEN": null, "MANAGING_AGENCY_NAME": "City of Austin Parks and Recreation", "ADDRESS": "3800 Mount Bonnell Rd., Austin, Texas 78731", "AMENITY_NAME": "Covert Park at Mount Bonnell Picnic Table 2"}, "type": "Feature", "geometry": {"type": "Point", "coordinates": [-97.7733723295116, 30.3208489563321]}, "id": 1058}, {"properties": {"ACCESSIBILITY_STATUS": "Not Accessible", "PARK_ID": "213", "AMENITY_SIZE": null, "STREET_NUMBER": "3800", "WIDTH": null, "LONGITUDE": -97.77360139, "YEAR_BUILT": null, "CREATED_BY": "hardya", "OTHER_PROTECTIONS": " ", "ZIP_CODE": "78731", "MODIFIED_BY": "hardya", "PRORAGIS_ID": "10245", "LENGTH": null, "RESERVATIONS": "No", "ASSET_MGMT_ID": 213.4003, "COUNTY": "Travis", "AMENITY_CLASS": 17, "CREATED_DATE": 1426498047000, "STATE": "TX", "SIZE_UNITS": null, "PROTECTION_COMMENTS": null, "AMENITY_TYPE": "Picnic Table", "AMENITYOWNER_TYPE": "Municipal", "INDOOR_OUTDOOR": "Outdoor", "MODIFIED_DATE": 1427200700000, "LWCF_PROTECTION": " ", "CITY_MUNICIPAL": "Austin", "LATITUDE": 30.323718, "WIDTH_UNITS": null, "LENGTH_UNITS": null, "STREET_TYPE": "Rd.", "STREET_NAME": "Mount Bonnell", "AMENITY_ID": "4003", "MANAGINGAGENCY_TYPE": "Municipal", "DESCRIPTION": "Concrete; On Concrete Pad", "OBJECTID": 1630, "STATUS": "Open", "AMENITY_OWNER_NAME": "City of Austin Parks and Recreation", "YEAR_OPEN": null, "MANAGING_AGENCY_NAME": "City of Austin Parks and Recreation", "ADDRESS": "3800 Mount Bonnell Rd., Austin, Texas 78731", "AMENITY_NAME": "Covert Park at Mount Bonnell Picnic Table 3"}, "type": "Feature", "geometry": {"type": "Point", "coordinates": [-97.7736013865502, 30.323717999676]}, "id": 1630}, {"properties": {"ACCESSIBILITY_STATUS": "Not Accessible", "PARK_ID": "213", "AMENITY_SIZE": null, "STREET_NUMBER": "3800", "WIDTH": null, "LONGITUDE": -97.77353563, "YEAR_BUILT": null, "CREATED_BY": "hardya", "OTHER_PROTECTIONS": " ", "ZIP_CODE": "78731", "MODIFIED_BY": "hardya", "PRORAGIS_ID": "10243", "LENGTH": null, "RESERVATIONS": "No", "ASSET_MGMT_ID": 213.4001, "COUNTY": "Travis", "AMENITY_CLASS": 17, "CREATED_DATE": 1426497431000, "STATE": "TX", "SIZE_UNITS": null, "PROTECTION_COMMENTS": null, "AMENITY_TYPE": "Picnic Table", "AMENITYOWNER_TYPE": "Municipal", "INDOOR_OUTDOOR": "Outdoor", "MODIFIED_DATE": 1427200700000, "LWCF_PROTECTION": " ", "CITY_MUNICIPAL": "Austin", "LATITUDE": 30.32076544, "WIDTH_UNITS": null, "LENGTH_UNITS": null, "STREET_TYPE": "Rd.", "STREET_NAME": "Mount Bonnell", "AMENITY_ID": "4001", "MANAGINGAGENCY_TYPE": "Municipal", "DESCRIPTION": "Concrete; On Concrete Pad", "OBJECTID": 1742, "STATUS": "Open", "AMENITY_OWNER_NAME": "City of Austin Parks and Recreation", "YEAR_OPEN": null, "MANAGING_AGENCY_NAME": "City of Austin Parks and Recreation", "ADDRESS": "3800 Mount Bonnell Rd., Austin, Texas 78731", "AMENITY_NAME": "Covert Park at Mount Bonnell Picnic Table 1"}, "type": "Feature", "geometry": {"type": "Point", "coordinates": [-97.773535625848, 30.3207654435801]}, "id": 1742}]}