{"features": [{"geometry": {"coordinates": [-97.7300649955557, 30.2712896738271], "type": "Point"}, "id": 396, "properties": {"WIDTH_UNITS": null, "LENGTH": null, "MODIFIED_DATE": 1427200692000, "DESCRIPTION": "1 Wood Bench", "AMENITY_ID": "4001", "PRORAGIS_ID": "523", "YEAR_BUILT": null, "STREET_NUMBER": "1180", "STATUS": "Open", "LWCF_PROTECTION": " ", "AMENITY_OWNER_NAME": "City of Austin Parks and Recreation", "INDOOR_OUTDOOR": "Outdoor", "CREATED_BY": "hardya", "CITY_MUNICIPAL": "Austin", "PROTECTION_COMMENTS": null, "YEAR_OPEN": null, "STREET_NAME": "Curve", "AMENITY_NAME": "Lott Pocket Park Bench", "LONGITUDE": -97.730065, "MANAGING_AGENCY_NAME": "City of Austin Parks and Recreation", "SIZE_UNITS": null, "LENGTH_UNITS": null, "STATE": "TX", "AMENITYOWNER_TYPE": "Municipal", "ADDRESS": "1180 Curve St., Austin, Texas 78702", "RESERVATIONS": "No", "ZIP_CODE": "78702", "PARK_ID": "198", "COUNTY": "Travis", "MODIFIED_BY": "hardya", "OTHER_PROTECTIONS": " ", "AMENITY_CLASS": 17, "OBJECTID": 396, "STREET_TYPE": "St.", "CREATED_DATE": 1407153796000, "LATITUDE": 30.27128967, "WIDTH": null, "AMENITY_TYPE": "Bench", "MANAGINGAGENCY_TYPE": "Municipal", "AMENITY_SIZE": null, "ASSET_MGMT_ID": 198.4001, "ACCESSIBILITY_STATUS": "Not Accessible"}, "type": "Feature"}, {"geometry": {"coordinates": [-97.729946071173, 30.2710462208505], "type": "Point"}, "id": 462, "properties": {"WIDTH_UNITS": null, "LENGTH": null, "MODIFIED_DATE": 1427200699000, "DESCRIPTION": "3 Human Spouts; 0 Dog Bowls; 0 Hose Bibs; Unknown Spout Type; Near Sprayground", "AMENITY_ID": "3003", "PRORAGIS_ID": "2601", "YEAR_BUILT": null, "STREET_NUMBER": "1180", "STATUS": "Open", "LWCF_PROTECTION": " ", "AMENITY_OWNER_NAME": "City of Austin Parks and Recreation", "INDOOR_OUTDOOR": "Outdoor", "CREATED_BY": "hardya", "CITY_MUNICIPAL": "Austin", "PROTECTION_COMMENTS": null, "YEAR_OPEN": null, "STREET_NAME": "Curve", "AMENITY_NAME": "Lott Pocket Park Drinking Fountain", "LONGITUDE": -97.72994607, "MANAGING_AGENCY_NAME": "City of Austin Parks and Recreation", "SIZE_UNITS": null, "LENGTH_UNITS": null, "STATE": "TX", "AMENITYOWNER_TYPE": "Municipal", "ADDRESS": "1180 Curve St., Austin, Texas 78702", "RESERVATIONS": "No", "ZIP_CODE": "78702", "PARK_ID": "198", "COUNTY": "Travis", "MODIFIED_BY": "hardya", "OTHER_PROTECTIONS": " ", "AMENITY_CLASS": 15, "OBJECTID": 462, "STREET_TYPE": "St.", "CREATED_DATE": 1421236731000, "LATITUDE": 30.27104622, "WIDTH": null, "AMENITY_TYPE": "Drinking Fountain", "MANAGINGAGENCY_TYPE": "Municipal", "AMENITY_SIZE": null, "ASSET_MGMT_ID": 198.3003, "ACCESSIBILITY_STATUS": "Accessible"}, "type": "Feature"}, {"geometry": {"coordinates": [-97.7300619464074, 30.2710047049276], "type": "Point"}, "id": 1437, "properties": {"WIDTH_UNITS": null, "LENGTH": null, "MODIFIED_DATE": 1427200700000, "DESCRIPTION": "Metal; On Concrete Pad", "AMENITY_ID": "4002", "PRORAGIS_ID": "9309", "YEAR_BUILT": null, "STREET_NUMBER": "1180", "STATUS": "Open", "LWCF_PROTECTION": " ", "AMENITY_OWNER_NAME": "City of Austin Parks and Recreation", "INDOOR_OUTDOOR": "Outdoor", "CREATED_BY": "hardya", "CITY_MUNICIPAL": "Austin", "PROTECTION_COMMENTS": null, "YEAR_OPEN": null, "STREET_NAME": "Curve", "AMENITY_NAME": "Lott Pocket Park Picnic Table", "LONGITUDE": -97.73006195, "MANAGING_AGENCY_NAME": "City of Austin Parks and Recreation", "SIZE_UNITS": null, "LENGTH_UNITS": null, "STATE": "TX", "AMENITYOWNER_TYPE": "Municipal", "ADDRESS": "1180 Curve St., Austin, Texas 78702", "RESERVATIONS": "No", "ZIP_CODE": "78702", "PARK_ID": "198", "COUNTY": "Travis", "MODIFIED_BY": "hardya", "OTHER_PROTECTIONS": " ", "AMENITY_CLASS": 17, "OBJECTID": 1437, "STREET_TYPE": "St.", "CREATED_DATE": 1425299155000, "LATITUDE": 30.2710047, "WIDTH": null, "AMENITY_TYPE": "Picnic Table", "MANAGINGAGENCY_TYPE": "Municipal", "AMENITY_SIZE": null, "ASSET_MGMT_ID": 198.4002, "ACCESSIBILITY_STATUS": "Accessible"}, "type": "Feature"}], "type": "FeatureCollection"}