{"features": [{"id": 60, "geometry": {"coordinates": [-97.7921083738611, 30.2292035089696], "type": "Point"}, "type": "Feature", "properties": {"YEAR_BUILT": null, "ZIP_CODE": "78745", "PRORAGIS_ID": "2584", "PROTECTION_COMMENTS": null, "COUNTY": "Travis", "RESERVATIONS": "No", "LENGTH": null, "OBJECTID": 60, "PARK_ID": "183", "MODIFIED_BY": "hardya", "AMENITY_OWNER_NAME": "City of Austin Parks and Recreation", "YEAR_OPEN": null, "AMENITYOWNER_TYPE": "Municipal", "INDOOR_OUTDOOR": "Outdoor", "OTHER_PROTECTIONS": " ", "ACCESSIBILITY_STATUS": "Not Accessible", "WIDTH": null, "STREET_NUMBER": "2106", "AMENITY_SIZE": null, "WIDTH_UNITS": null, "LONGITUDE": -97.79210837, "CREATED_DATE": 1421232436000, "AMENITY_NAME": "Joslin Neighborhood Park Drinking Fountain", "ASSET_MGMT_ID": 183.3001, "CREATED_BY": "hardya", "STATUS": "Open", "CITY_MUNICIPAL": "Austin", "MODIFIED_DATE": 1427200692000, "MANAGINGAGENCY_TYPE": "Municipal", "STREET_TYPE": "Trl.", "MANAGING_AGENCY_NAME": "City of Austin Parks and Recreation", "AMENITY_CLASS": 15, "SIZE_UNITS": null, "LWCF_PROTECTION": " ", "STREET_NAME": "Cimaron", "DESCRIPTION": "1 Human Spouts; 0 Dog Bowls; 0 Hose Bibs; Central Spout Type; Near Mixed Use Field", "AMENITY_ID": "3001", "ADDRESS": "2106 Cimaron Trl., Austin, Texas 78745", "LATITUDE": 30.22920351, "STATE": "TX", "LENGTH_UNITS": null, "AMENITY_TYPE": "Drinking Fountain"}}, {"id": 771, "geometry": {"coordinates": [-97.7920418653788, 30.2291476318381], "type": "Point"}, "type": "Feature", "properties": {"YEAR_BUILT": null, "ZIP_CODE": "78745", "PRORAGIS_ID": "8977", "PROTECTION_COMMENTS": null, "COUNTY": "Travis", "RESERVATIONS": "No", "LENGTH": null, "OBJECTID": 771, "PARK_ID": "183", "MODIFIED_BY": "hardya", "AMENITY_OWNER_NAME": "City of Austin Parks and Recreation", "YEAR_OPEN": null, "AMENITYOWNER_TYPE": "Municipal", "INDOOR_OUTDOOR": "Outdoor", "OTHER_PROTECTIONS": " ", "ACCESSIBILITY_STATUS": "Not Accessible", "WIDTH": null, "STREET_NUMBER": "2106", "AMENITY_SIZE": null, "WIDTH_UNITS": null, "LONGITUDE": -97.79204187, "CREATED_DATE": 1425049915000, "AMENITY_NAME": "Joslin Neighborhood Park: Mixed Use Field Picnic Table", "ASSET_MGMT_ID": 183.4001, "CREATED_BY": "hardya", "STATUS": "Open", "CITY_MUNICIPAL": "Austin", "MODIFIED_DATE": 1427200700000, "MANAGINGAGENCY_TYPE": "Municipal", "STREET_TYPE": "Trl.", "MANAGING_AGENCY_NAME": "City of Austin Parks and Recreation", "AMENITY_CLASS": 17, "SIZE_UNITS": null, "LWCF_PROTECTION": " ", "STREET_NAME": "Cimaron", "DESCRIPTION": "Metal; No Concrete Pad", "AMENITY_ID": "4001", "ADDRESS": "2106 Cimaron Trl., Austin, Texas 78745", "LATITUDE": 30.22914763, "STATE": "TX", "LENGTH_UNITS": null, "AMENITY_TYPE": "Picnic Table"}}, {"id": 1746, "geometry": {"coordinates": [-97.7921251306137, 30.2286104091695], "type": "Point"}, "type": "Feature", "properties": {"YEAR_BUILT": null, "ZIP_CODE": "78745", "PRORAGIS_ID": "8978", "PROTECTION_COMMENTS": null, "COUNTY": "Travis", "RESERVATIONS": "No", "LENGTH": null, "OBJECTID": 1746, "PARK_ID": "183", "MODIFIED_BY": "hardya", "AMENITY_OWNER_NAME": "City of Austin Parks and Recreation", "YEAR_OPEN": null, "AMENITYOWNER_TYPE": "Municipal", "INDOOR_OUTDOOR": "Outdoor", "OTHER_PROTECTIONS": " ", "ACCESSIBILITY_STATUS": "Not Accessible", "WIDTH": null, "STREET_NUMBER": "2106", "AMENITY_SIZE": null, "WIDTH_UNITS": null, "LONGITUDE": -97.79212513, "CREATED_DATE": 1425050166000, "AMENITY_NAME": "Joslin Neighborhood Park Picnic Table", "ASSET_MGMT_ID": 183.4002, "CREATED_BY": "hardya", "STATUS": "Open", "CITY_MUNICIPAL": "Austin", "MODIFIED_DATE": 1427200700000, "MANAGINGAGENCY_TYPE": "Municipal", "STREET_TYPE": "Trl.", "MANAGING_AGENCY_NAME": "City of Austin Parks and Recreation", "AMENITY_CLASS": 17, "SIZE_UNITS": null, "LWCF_PROTECTION": " ", "STREET_NAME": "Cimaron", "DESCRIPTION": "Metal; No Concrete Pad", "AMENITY_ID": "4002", "ADDRESS": "2106 Cimaron Trl., Austin, Texas 78745", "LATITUDE": 30.22861041, "STATE": "TX", "LENGTH_UNITS": null, "AMENITY_TYPE": "Picnic Table"}}], "type": "FeatureCollection"}