{"type": "FeatureCollection", "features": [{"properties": {"ACCESSIBILITY_STATUS": "Not Accessible", "PARK_ID": "254", "AMENITY_SIZE": null, "STREET_NUMBER": "405", "WIDTH": null, "LONGITUDE": -97.72070658, "YEAR_BUILT": null, "CREATED_BY": "hardya", "OTHER_PROTECTIONS": " ", "ZIP_CODE": "78752", "MODIFIED_BY": "hardya", "PRORAGIS_ID": "2881", "LENGTH": null, "RESERVATIONS": "No", "ASSET_MGMT_ID": 254.3001, "COUNTY": "Travis", "AMENITY_CLASS": 15, "CREATED_DATE": 1421314417000, "STATE": "TX", "SIZE_UNITS": null, "PROTECTION_COMMENTS": null, "AMENITY_TYPE": "Drinking Fountain", "AMENITYOWNER_TYPE": "School", "INDOOR_OUTDOOR": "Outdoor", "MODIFIED_DATE": 1427200699000, "LWCF_PROTECTION": " ", "CITY_MUNICIPAL": "Austin", "LATITUDE": 30.32779907, "WIDTH_UNITS": null, "LENGTH_UNITS": null, "STREET_TYPE": "Dr.", "STREET_NAME": "Denson", "AMENITY_ID": "3001", "MANAGINGAGENCY_TYPE": "Municipal", "DESCRIPTION": "1 Human Spouts; 0 Dog Bowl; 0 Hose Bibs; Central Spout Type; Next to Pavilion", "OBJECTID": 883, "STATUS": "Open", "AMENITY_OWNER_NAME": "Austin Independent School District", "YEAR_OPEN": null, "MANAGING_AGENCY_NAME": "City of Austin Parks and Recreation", "ADDRESS": "405 Denson Dr., Austin, Texas 78752", "AMENITY_NAME": "Reilly School Park Drinking Fountain"}, "type": "Feature", "geometry": {"type": "Point", "coordinates": [-97.7207065746873, 30.3277990666507]}, "id": 883}]}