{"type": "FeatureCollection", "features": [{"properties": {"ACCESSIBILITY_STATUS": "Not Accessible", "PARK_ID": "117", "STREET_NUMBER": "121", "WIDTH": null, "LONGITUDE": -97.76751849, "YEAR_BUILT": null, "PARD_ID_1": 117, "CREATED_BY": "<Null>", "FACILITY_TYPE": "Basketball", "OTHER_PROTECTIONS": " ", "ZIP_CODE": "78745", "MODIFIED_BY": "hardya", "PRORAGIS_ID": "184", "PROTECTION_COMMENTS": null, "RESERVATIONS": "No", "ASSET_MGMT_ID": 117.301, "COUNTY": "Travis", "CREATED_DATE": 1021507200000, "STATE": "TX", "SIZE_UNITS": null, "MODIFIED_DATE": 1392289054000, "FACILITY_SIZE": null, "FACILITY_OWNER_NAME": "City of Austin Parks and Recreation", "INDOOR_OUTDOOR": "Outdoor", "FACILITY_NAME": "Battle Bend Neighborhood Park Basketball Court", "LWCF_PROTECTION": " ", "CITY_MUNICIPAL": "Austin", "LATITUDE": 30.2138843, "WIDTH_UNITS": null, "FACILITY_ID": "301", "STREET_TYPE": "Ave.", "STREET_NAME": "Sheraton ", "LENGTH": null, "MANAGINGAGENCY_TYPE": "Municipal", "DESCRIPTION": "Full Court; Not Sheltered; 2 Goals", "OBJECTID": 1622, "FACILITYOWNER_TYPE": "Municipal", "STATUS": "Open", "YEAR_OPEN": null, "MANAGING_AGENCY_NAME": "City of Austin Parks and Recreation", "ADDRESS": "121 Sheraton Ave., Austin, Texas 78745", "LENGTH_UNITS": null, "FACILITY_CLASS": 8}, "type": "Feature", "geometry": {"type": "Point", "coordinates": [-97.7675184856076, 30.2138842950996]}, "id": 1622}, {"properties": {"ACCESSIBILITY_STATUS": "Not Accessible", "PARK_ID": "117", "STREET_NUMBER": "121", "WIDTH": null, "LONGITUDE": -97.76768635, "YEAR_BUILT": null, "PARD_ID_1": 117, "CREATED_BY": "hardya", "FACILITY_TYPE": "Gazebo", "OTHER_PROTECTIONS": " ", "ZIP_CODE": "78745", "MODIFIED_BY": "hardya", "PRORAGIS_ID": "185", "PROTECTION_COMMENTS": null, "RESERVATIONS": "No", "ASSET_MGMT_ID": 117.1601, "COUNTY": "Travis", "CREATED_DATE": 1352366398000, "STATE": "TX", "SIZE_UNITS": "Square Feet", "MODIFIED_DATE": 1392289056000, "FACILITY_SIZE": 400, "FACILITY_OWNER_NAME": "City of Austin Parks and Recreation", "INDOOR_OUTDOOR": "Outdoor", "FACILITY_NAME": "Battle Bend Neighborhood Park Gazebo", "LWCF_PROTECTION": " ", "CITY_MUNICIPAL": "Austin", "LATITUDE": 30.21418474, "WIDTH_UNITS": null, "FACILITY_ID": "1601", "STREET_TYPE": "Ave.", "STREET_NAME": "Sheraton ", "LENGTH": null, "MANAGINGAGENCY_TYPE": "Municipal", "DESCRIPTION": "Covered Roof; 3 Benches", "OBJECTID": 1623, "FACILITYOWNER_TYPE": "Municipal", "STATUS": "Open", "YEAR_OPEN": null, "MANAGING_AGENCY_NAME": "City of Austin Parks and Recreation", "ADDRESS": "121 Sheraton Ave., Austin, Texas 78745", "LENGTH_UNITS": null, "FACILITY_CLASS": 16}, "type": "Feature", "geometry": {"type": "Point", "coordinates": [-97.7676863454256, 30.214184735946]}, "id": 1623}, {"properties": {"ACCESSIBILITY_STATUS": "Accessible", "PARK_ID": "117", "STREET_NUMBER": "121", "WIDTH": null, "LONGITUDE": -97.76791433, "YEAR_BUILT": null, "PARD_ID_1": 117, "CREATED_BY": "hardya", "FACILITY_TYPE": "Playground", "OTHER_PROTECTIONS": " ", "ZIP_CODE": "78745", "MODIFIED_BY": "hardya", "PRORAGIS_ID": "186", "PROTECTION_COMMENTS": null, "RESERVATIONS": "No", "ASSET_MGMT_ID": 117.1401, "COUNTY": "Travis", "CREATED_DATE": 1359504000000, "STATE": "TX", "SIZE_UNITS": null, "MODIFIED_DATE": 1392289058000, "FACILITY_SIZE": null, "FACILITY_OWNER_NAME": "City of Austin Parks and Recreation", "INDOOR_OUTDOOR": "Outdoor", "FACILITY_NAME": "Battle Bend Neighborhood Park Playground", "LWCF_PROTECTION": " ", "CITY_MUNICIPAL": "Austin", "LATITUDE": 30.21416728, "WIDTH_UNITS": null, "FACILITY_ID": "1401", "STREET_TYPE": "Ave.", "STREET_NAME": "Sheraton ", "LENGTH": null, "MANAGINGAGENCY_TYPE": "Municipal", "DESCRIPTION": "Peagravel/PIP;1 Tot Playscape;1 Youth Playscape;1 Tot Swing(1 Bay, 2 Buckets)", "OBJECTID": 1624, "FACILITYOWNER_TYPE": "Municipal", "STATUS": "Open", "YEAR_OPEN": null, "MANAGING_AGENCY_NAME": "City of Austin Parks and Recreation", "ADDRESS": "121 Sheraton Ave., Austin, Texas 78745", "LENGTH_UNITS": null, "FACILITY_CLASS": 3}, "type": "Feature", "geometry": {"type": "Point", "coordinates": [-97.7679143278681, 30.214167284523]}, "id": 1624}]}