{"features": [{"geometry": {"coordinates": [-97.7035998884451, 30.2716918712024], "type": "Point"}, "id": 16, "properties": {"WIDTH_UNITS": null, "LENGTH": null, "FACILITY_CLASS": 8, "DESCRIPTION": "Full Court; Sheltered with ShadeCloth; 2 Goals", "PRORAGIS_ID": "1452", "YEAR_BUILT": null, "STREET_NUMBER": "2806", "STATUS": "Open_Restricted", "FACILITY_ID": "301", "LWCF_PROTECTION": " ", "LONGITUDE": -97.70359989, "CREATED_BY": "<Null>", "CITY_MUNICIPAL": "Austin", "PROTECTION_COMMENTS": null, "YEAR_OPEN": null, "STREET_NAME": "Goodwin", "MANAGING_AGENCY_NAME": "City of Austin Parks and Recreation", "ASSET_MGMT_ID": 224.301, "SIZE_UNITS": null, "MODIFIED_BY": "hardya", "LENGTH_UNITS": null, "ACCESSIBILITY_STATUS": "Not Accessible", "STATE": "TX", "FACILITY_TYPE": "Basketball", "ADDRESS": "2806 Goodwin Ave., Austin, Texas 78702", "RESERVATIONS": "No", "ZIP_CODE": "78702", "PARK_ID": "224", "COUNTY": "Travis", "PARD_ID_1": 224, "OTHER_PROTECTIONS": " ", "OBJECTID": 16, "FACILITYOWNER_TYPE": "School", "STREET_TYPE": "Ave.", "CREATED_DATE": 1026950400000, "LATITUDE": 30.27169187, "WIDTH": null, "FACILITY_NAME": "Oak Springs School Park Basketball Court", "MANAGINGAGENCY_TYPE": "Municipal", "FACILITY_OWNER_NAME": "Austin Independent School District", "INDOOR_OUTDOOR": "Outdoor", "MODIFIED_DATE": 1392379250000, "FACILITY_SIZE": null}, "type": "Feature"}, {"geometry": {"coordinates": [-97.7044521860091, 30.2711371048757], "type": "Point"}, "id": 17, "properties": {"WIDTH_UNITS": null, "LENGTH": null, "FACILITY_CLASS": 20, "DESCRIPTION": "Concrete; 20 Regular Spaces/ 2 ADA Spaces/ School Parking", "PRORAGIS_ID": "1454", "YEAR_BUILT": null, "STREET_NUMBER": "2806", "STATUS": "Open_Restricted", "FACILITY_ID": "2001", "LWCF_PROTECTION": " ", "LONGITUDE": -97.70445219, "CREATED_BY": "<Null>", "CITY_MUNICIPAL": "Austin", "PROTECTION_COMMENTS": null, "YEAR_OPEN": null, "STREET_NAME": "Goodwin", "MANAGING_AGENCY_NAME": "Austin Independent School District", "ASSET_MGMT_ID": 224.2001, "SIZE_UNITS": null, "MODIFIED_BY": "hardya", "LENGTH_UNITS": null, "ACCESSIBILITY_STATUS": "Accessible", "STATE": "TX", "FACILITY_TYPE": "Parking Lot", "ADDRESS": "2806 Goodwin Ave., Austin, Texas 78702", "RESERVATIONS": "No", "ZIP_CODE": "78702", "PARK_ID": "224", "COUNTY": "Travis", "PARD_ID_1": 224, "OTHER_PROTECTIONS": " ", "OBJECTID": 17, "FACILITYOWNER_TYPE": "School", "STREET_TYPE": "Ave.", "CREATED_DATE": 1026950400000, "LATITUDE": 30.2711371, "WIDTH": null, "FACILITY_NAME": "Oak Springs School Park Parking Lot", "MANAGINGAGENCY_TYPE": "School", "FACILITY_OWNER_NAME": "Austin Independent School District", "INDOOR_OUTDOOR": "Outdoor", "MODIFIED_DATE": 1392379254000, "FACILITY_SIZE": null}, "type": "Feature"}, {"geometry": {"coordinates": [-97.7031618637322, 30.272116905368], "type": "Point"}, "id": 1416, "properties": {"WIDTH_UNITS": null, "LENGTH": null, "FACILITY_CLASS": 10, "DESCRIPTION": "No Backstop; No Goals; No Lights; No Stands; No Scoreboard", "PRORAGIS_ID": "1453", "YEAR_BUILT": null, "STREET_NUMBER": "2806", "STATUS": "Open_Restricted", "FACILITY_ID": "1901", "LWCF_PROTECTION": " ", "LONGITUDE": -97.70316186, "CREATED_BY": "hardya", "CITY_MUNICIPAL": "Austin", "PROTECTION_COMMENTS": null, "YEAR_OPEN": null, "STREET_NAME": "Goodwin", "MANAGING_AGENCY_NAME": "City of Austin Parks and Recreation", "ASSET_MGMT_ID": 224.1901, "SIZE_UNITS": null, "MODIFIED_BY": "hardya", "LENGTH_UNITS": null, "ACCESSIBILITY_STATUS": "Not Accessible", "STATE": "TX", "FACILITY_TYPE": "Mixed Use Field", "ADDRESS": "2806 Goodwin Ave., Austin, Texas 78702", "RESERVATIONS": "Yes", "ZIP_CODE": "78702", "PARK_ID": "224", "COUNTY": "Travis", "PARD_ID_1": 224, "OTHER_PROTECTIONS": " ", "OBJECTID": 1416, "FACILITYOWNER_TYPE": "School", "STREET_TYPE": "Ave.", "CREATED_DATE": 1199145600000, "LATITUDE": 30.27211691, "WIDTH": null, "FACILITY_NAME": "Oak Springs School Park Mixed Use Field", "MANAGINGAGENCY_TYPE": "Municipal", "FACILITY_OWNER_NAME": "Austin Independent School District", "INDOOR_OUTDOOR": "Outdoor", "MODIFIED_DATE": 1398089599000, "FACILITY_SIZE": null}, "type": "Feature"}], "type": "FeatureCollection"}