{"features": [{"geometry": {"coordinates": [-97.7643972174611, 30.1810890228019], "type": "Point"}, "id": 2077, "properties": {"WIDTH_UNITS": null, "LENGTH": null, "FACILITY_CLASS": 3, "DESCRIPTION": "Peagravel/PIP;1 Tot Playscape(Tree Canopy)", "PRORAGIS_ID": "1008", "YEAR_BUILT": null, "STREET_NUMBER": "2203", "STATUS": "Open", "FACILITY_ID": "1401", "LWCF_PROTECTION": " ", "LONGITUDE": -97.76439722, "CREATED_BY": "hardya", "CITY_MUNICIPAL": "Austin", "PROTECTION_COMMENTS": null, "YEAR_OPEN": null, "STREET_NAME": "Blue Meadow", "MANAGING_AGENCY_NAME": "City of Austin Parks and Recreation", "ASSET_MGMT_ID": 186.1401, "SIZE_UNITS": null, "MODIFIED_BY": "hardya", "LENGTH_UNITS": null, "ACCESSIBILITY_STATUS": "Accessible", "STATE": "TX", "FACILITY_TYPE": "Playground", "ADDRESS": "2203 Blue Meadow Dr., Austin, Texas 78744", "RESERVATIONS": "No", "ZIP_CODE": "78744", "PARK_ID": "186", "COUNTY": "Travis", "PARD_ID_1": 186, "OTHER_PROTECTIONS": " ", "OBJECTID": 2077, "FACILITYOWNER_TYPE": "Municipal", "STREET_TYPE": "Dr.", "CREATED_DATE": 1359331200000, "LATITUDE": 30.18108902, "WIDTH": null, "FACILITY_NAME": "Kendra Page Neighborhood Park Tot Playground", "MANAGINGAGENCY_TYPE": "Municipal", "FACILITY_OWNER_NAME": "City of Austin Parks and Recreation", "INDOOR_OUTDOOR": "Outdoor", "MODIFIED_DATE": 1392305015000, "FACILITY_SIZE": null}, "type": "Feature"}, {"geometry": {"coordinates": [-97.7644680594102, 30.1808664957989], "type": "Point"}, "id": 2078, "properties": {"WIDTH_UNITS": null, "LENGTH": null, "FACILITY_CLASS": 8, "DESCRIPTION": "Sand Court; No Lights", "PRORAGIS_ID": "1009", "YEAR_BUILT": null, "STREET_NUMBER": "2203", "STATUS": "Open", "FACILITY_ID": "301", "LWCF_PROTECTION": " ", "LONGITUDE": -97.76446806, "CREATED_BY": "hardya", "CITY_MUNICIPAL": "Austin", "PROTECTION_COMMENTS": null, "YEAR_OPEN": null, "STREET_NAME": "Blue Meadow", "MANAGING_AGENCY_NAME": "City of Austin Parks and Recreation", "ASSET_MGMT_ID": 186.301, "SIZE_UNITS": null, "MODIFIED_BY": "hardya", "LENGTH_UNITS": null, "ACCESSIBILITY_STATUS": "Not Accessible", "STATE": "TX", "FACILITY_TYPE": "Volleyball", "ADDRESS": "2203 Blue Meadow Dr., Austin, Texas 78744", "RESERVATIONS": "No", "ZIP_CODE": "78744", "PARK_ID": "186", "COUNTY": "Travis", "PARD_ID_1": 186, "OTHER_PROTECTIONS": " ", "OBJECTID": 2078, "FACILITYOWNER_TYPE": "Municipal", "STREET_TYPE": "Dr.", "CREATED_DATE": 1352419200000, "LATITUDE": 30.1808665, "WIDTH": null, "FACILITY_NAME": "Kendra Page Neighborhood Park Volleyball Court", "MANAGINGAGENCY_TYPE": "Municipal", "FACILITY_OWNER_NAME": "City of Austin Parks and Recreation", "INDOOR_OUTDOOR": "Outdoor", "MODIFIED_DATE": 1392305017000, "FACILITY_SIZE": null}, "type": "Feature"}, {"geometry": {"coordinates": [-97.7645887073297, 30.1811241517929], "type": "Point"}, "id": 2079, "properties": {"WIDTH_UNITS": null, "LENGTH": null, "FACILITY_CLASS": 3, "DESCRIPTION": "Peagravel/PIP;1 Youth Playscape(Tree Canopy)", "PRORAGIS_ID": "1010", "YEAR_BUILT": null, "STREET_NUMBER": "2203", "STATUS": "Open", "FACILITY_ID": "1402", "LWCF_PROTECTION": " ", "LONGITUDE": -97.76458871, "CREATED_BY": "hardya", "CITY_MUNICIPAL": "Austin", "PROTECTION_COMMENTS": null, "YEAR_OPEN": null, "STREET_NAME": "Blue Meadow", "MANAGING_AGENCY_NAME": "City of Austin Parks and Recreation", "ASSET_MGMT_ID": 186.1402, "SIZE_UNITS": null, "MODIFIED_BY": "hardya", "LENGTH_UNITS": null, "ACCESSIBILITY_STATUS": "Accessible", "STATE": "TX", "FACILITY_TYPE": "Playground", "ADDRESS": "2203 Blue Meadow Dr., Austin, Texas 78744", "RESERVATIONS": "No", "ZIP_CODE": "78744", "PARK_ID": "186", "COUNTY": "Travis", "PARD_ID_1": 186, "OTHER_PROTECTIONS": " ", "OBJECTID": 2079, "FACILITYOWNER_TYPE": "Municipal", "STREET_TYPE": "Dr.", "CREATED_DATE": 1359331200000, "LATITUDE": 30.18112415, "WIDTH": null, "FACILITY_NAME": "Kendra Page Neighborhood Park Youth Playground", "MANAGINGAGENCY_TYPE": "Municipal", "FACILITY_OWNER_NAME": "City of Austin Parks and Recreation", "INDOOR_OUTDOOR": "Outdoor", "MODIFIED_DATE": 1392305022000, "FACILITY_SIZE": null}, "type": "Feature"}], "type": "FeatureCollection"}