{"type": "FeatureCollection", "features": [{"properties": {"ACCESSIBILITY_STATUS": "Not Accessible", "PARK_ID": "297", "STREET_NUMBER": "522", "WIDTH": null, "LONGITUDE": -97.71664011, "YEAR_BUILT": null, "PARD_ID_1": 297, "CREATED_BY": "hardya", "FACILITY_TYPE": "Scenic Overlook", "OTHER_PROTECTIONS": " ", "ZIP_CODE": "78741", "MODIFIED_BY": "hardya", "PRORAGIS_ID": "1137", "PROTECTION_COMMENTS": null, "RESERVATIONS": "No", "ASSET_MGMT_ID": 297.1701, "COUNTY": "Travis", "CREATED_DATE": 1352392741000, "STATE": "TX", "SIZE_UNITS": null, "MODIFIED_DATE": 1392305373000, "FACILITY_SIZE": null, "FACILITY_OWNER_NAME": "City of Austin Parks and Recreation", "INDOOR_OUTDOOR": "Outdoor", "FACILITY_NAME": "Longhorn Shores at Town Lake Metro Park Scenic Overlook", "LWCF_PROTECTION": " ", "CITY_MUNICIPAL": "Austin", "LATITUDE": 30.24462785, "WIDTH_UNITS": null, "FACILITY_ID": "1701", "STREET_TYPE": "Rd.", "STREET_NAME": "S Pleasant Valley", "LENGTH": null, "MANAGINGAGENCY_TYPE": "Municipal", "DESCRIPTION": "Overlooking Lady Bird Lake", "OBJECTID": 2112, "FACILITYOWNER_TYPE": "Municipal", "STATUS": "Open", "YEAR_OPEN": null, "MANAGING_AGENCY_NAME": "City of Austin Parks and Recreation", "ADDRESS": "522 S Pleasant Valley Rd., Austin, Texas 78741", "LENGTH_UNITS": null, "FACILITY_CLASS": 4}, "type": "Feature", "geometry": {"type": "Point", "coordinates": [-97.7166401087494, 30.244627845651]}, "id": 2112}, {"properties": {"ACCESSIBILITY_STATUS": "Accessible", "PARK_ID": "297", "STREET_NUMBER": "60", "WIDTH": null, "LONGITUDE": -97.71670262, "YEAR_BUILT": null, "PARD_ID_1": 297, "CREATED_BY": "hardya", "FACILITY_TYPE": "Memorial", "OTHER_PROTECTIONS": " ", "ZIP_CODE": "78741", "MODIFIED_BY": "roosg", "PRORAGIS_ID": "3295", "PROTECTION_COMMENTS": null, "RESERVATIONS": "No", "ASSET_MGMT_ID": 297.1001, "COUNTY": "Travis", "CREATED_DATE": 1394809470000, "STATE": "TX", "SIZE_UNITS": null, "MODIFIED_DATE": 1427883971000, "FACILITY_SIZE": null, "FACILITY_OWNER_NAME": "City of Austin Parks and Recreation", "INDOOR_OUTDOOR": "Outdoor", "FACILITY_NAME": "Longhorn Shores at Town Lake Metro Park: Jeremy D. Payne Memorial Bench", "LWCF_PROTECTION": " ", "CITY_MUNICIPAL": "Austin", "LATITUDE": 30.24461662, "WIDTH_UNITS": null, "FACILITY_ID": "1001", "STREET_TYPE": "Rd.", "STREET_NAME": "S Pleasant Valley", "LENGTH": null, "MANAGINGAGENCY_TYPE": "Municipal", "DESCRIPTION": "1 Metal Bench; Plaque Missing As Of April 2015 Survey", "OBJECTID": 2544, "FACILITYOWNER_TYPE": "Municipal", "STATUS": "Open", "YEAR_OPEN": null, "MANAGING_AGENCY_NAME": "City of Austin Parks and Recreation", "ADDRESS": "60 S Pleasant Valley Rd., Austin, Texas 78741", "LENGTH_UNITS": null, "FACILITY_CLASS": 11}, "type": "Feature", "geometry": {"type": "Point", "coordinates": [-97.7167026210751, 30.2446166160666]}, "id": 2544}]}