{"features": [{"properties": {"PARD_ID_1": 297, "COUNTY": "Travis", "MODIFIED_BY": "hardya", "INDOOR_OUTDOOR": "Outdoor", "RESERVATIONS": "No", "PROTECTION_COMMENTS": null, "LWCF_PROTECTION": " ", "WIDTH": null, "FACILITY_OWNER_NAME": "City of Austin Parks and Recreation", "MANAGINGAGENCY_TYPE": "Municipal", "FACILITY_TYPE": "Scenic Overlook", "OTHER_PROTECTIONS": " ", "FACILITY_NAME": "Longhorn Shores at Town Lake Metro Park Scenic Overlook", "LENGTH_UNITS": null, "LATITUDE": 30.24462785, "ASSET_MGMT_ID": 297.1701, "STATUS": "Open", "YEAR_BUILT": null, "FACILITY_SIZE": null, "LONGITUDE": -97.71664011, "MODIFIED_DATE": 1392305373000, "CITY_MUNICIPAL": "Austin", "MANAGING_AGENCY_NAME": "City of Austin Parks and Recreation", "FACILITY_ID": "1701", "SIZE_UNITS": null, "DESCRIPTION": "Overlooking Lady Bird Lake", "ADDRESS": "522 S Pleasant Valley Rd., Austin, Texas 78741", "WIDTH_UNITS": null, "ACCESSIBILITY_STATUS": "Not Accessible", "STREET_NUMBER": "522", "ZIP_CODE": "78741", "YEAR_OPEN": null, "PARK_ID": "297", "FACILITY_CLASS": 4, "CREATED_DATE": 1352392741000, "CREATED_BY": "hardya", "STREET_NAME": "S Pleasant Valley", "STREET_TYPE": "Rd.", "PRORAGIS_ID": "1137", "OBJECTID": 2112, "STATE": "TX", "FACILITYOWNER_TYPE": "Municipal", "LENGTH": null}, "id": 2112, "geometry": {"coordinates": [-97.7166401087494, 30.244627845651], "type": "Point"}, "type": "Feature"}, {"properties": {"PARD_ID_1": 297, "COUNTY": "Travis", "MODIFIED_BY": "roosg", "INDOOR_OUTDOOR": "Outdoor", "RESERVATIONS": "No", "PROTECTION_COMMENTS": null, "LWCF_PROTECTION": " ", "WIDTH": null, "FACILITY_OWNER_NAME": "City of Austin Parks and Recreation", "MANAGINGAGENCY_TYPE": "Municipal", "FACILITY_TYPE": "Memorial", "OTHER_PROTECTIONS": " ", "FACILITY_NAME": "Longhorn Shores at Town Lake Metro Park: Jeremy D. Payne Memorial Bench", "LENGTH_UNITS": null, "LATITUDE": 30.24461662, "ASSET_MGMT_ID": 297.1001, "STATUS": "Open", "YEAR_BUILT": null, "FACILITY_SIZE": null, "LONGITUDE": -97.71670262, "MODIFIED_DATE": 1427883971000, "CITY_MUNICIPAL": "Austin", "MANAGING_AGENCY_NAME": "City of Austin Parks and Recreation", "FACILITY_ID": "1001", "SIZE_UNITS": null, "DESCRIPTION": "1 Metal Bench; Plaque Missing As Of April 2015 Survey", "ADDRESS": "60 S Pleasant Valley Rd., Austin, Texas 78741", "WIDTH_UNITS": null, "ACCESSIBILITY_STATUS": "Accessible", "STREET_NUMBER": "60", "ZIP_CODE": "78741", "YEAR_OPEN": null, "PARK_ID": "297", "FACILITY_CLASS": 11, "CREATED_DATE": 1394809470000, "CREATED_BY": "hardya", "STREET_NAME": "S Pleasant Valley", "STREET_TYPE": "Rd.", "PRORAGIS_ID": "3295", "OBJECTID": 2544, "STATE": "TX", "FACILITYOWNER_TYPE": "Municipal", "LENGTH": null}, "id": 2544, "geometry": {"coordinates": [-97.7167026210751, 30.2446166160666], "type": "Point"}, "type": "Feature"}], "type": "FeatureCollection"}