{"features": [{"geometry": {"coordinates": [-97.7166401087494, 30.244627845651], "type": "Point"}, "id": 2112, "properties": {"WIDTH_UNITS": null, "LENGTH": null, "FACILITY_CLASS": 4, "DESCRIPTION": "Overlooking Lady Bird Lake", "PRORAGIS_ID": "1137", "YEAR_BUILT": null, "STREET_NUMBER": "522", "STATUS": "Open", "FACILITY_ID": "1701", "LWCF_PROTECTION": " ", "LONGITUDE": -97.71664011, "CREATED_BY": "hardya", "CITY_MUNICIPAL": "Austin", "PROTECTION_COMMENTS": null, "YEAR_OPEN": null, "STREET_NAME": "S Pleasant Valley", "MANAGING_AGENCY_NAME": "City of Austin Parks and Recreation", "ASSET_MGMT_ID": 297.1701, "SIZE_UNITS": null, "MODIFIED_BY": "hardya", "LENGTH_UNITS": null, "ACCESSIBILITY_STATUS": "Not Accessible", "STATE": "TX", "FACILITY_TYPE": "Scenic Overlook", "ADDRESS": "522 S Pleasant Valley Rd., Austin, Texas 78741", "RESERVATIONS": "No", "ZIP_CODE": "78741", "PARK_ID": "297", "COUNTY": "Travis", "PARD_ID_1": 297, "OTHER_PROTECTIONS": " ", "OBJECTID": 2112, "FACILITYOWNER_TYPE": "Municipal", "STREET_TYPE": "Rd.", "CREATED_DATE": 1352392741000, "LATITUDE": 30.24462785, "WIDTH": null, "FACILITY_NAME": "Longhorn Shores at Town Lake Metro Park Scenic Overlook", "MANAGINGAGENCY_TYPE": "Municipal", "FACILITY_OWNER_NAME": "City of Austin Parks and Recreation", "INDOOR_OUTDOOR": "Outdoor", "MODIFIED_DATE": 1392305373000, "FACILITY_SIZE": null}, "type": "Feature"}, {"geometry": {"coordinates": [-97.7167026210751, 30.2446166160666], "type": "Point"}, "id": 2544, "properties": {"WIDTH_UNITS": null, "LENGTH": null, "FACILITY_CLASS": 11, "DESCRIPTION": "1 Metal Bench; Plaque Missing As Of April 2015 Survey", "PRORAGIS_ID": "3295", "YEAR_BUILT": null, "STREET_NUMBER": "60", "STATUS": "Open", "FACILITY_ID": "1001", "LWCF_PROTECTION": " ", "LONGITUDE": -97.71670262, "CREATED_BY": "hardya", "CITY_MUNICIPAL": "Austin", "PROTECTION_COMMENTS": null, "YEAR_OPEN": null, "STREET_NAME": "S Pleasant Valley", "MANAGING_AGENCY_NAME": "City of Austin Parks and Recreation", "ASSET_MGMT_ID": 297.1001, "SIZE_UNITS": null, "MODIFIED_BY": "roosg", "LENGTH_UNITS": null, "ACCESSIBILITY_STATUS": "Accessible", "STATE": "TX", "FACILITY_TYPE": "Memorial", "ADDRESS": "60 S Pleasant Valley Rd., Austin, Texas 78741", "RESERVATIONS": "No", "ZIP_CODE": "78741", "PARK_ID": "297", "COUNTY": "Travis", "PARD_ID_1": 297, "OTHER_PROTECTIONS": " ", "OBJECTID": 2544, "FACILITYOWNER_TYPE": "Municipal", "STREET_TYPE": "Rd.", "CREATED_DATE": 1394809470000, "LATITUDE": 30.24461662, "WIDTH": null, "FACILITY_NAME": "Longhorn Shores at Town Lake Metro Park: Jeremy D. Payne Memorial Bench", "MANAGINGAGENCY_TYPE": "Municipal", "FACILITY_OWNER_NAME": "City of Austin Parks and Recreation", "INDOOR_OUTDOOR": "Outdoor", "MODIFIED_DATE": 1427883971000, "FACILITY_SIZE": null}, "type": "Feature"}], "type": "FeatureCollection"}