{"features": [{"geometry": {"coordinates": [-97.8321097561376, 30.1938954854767], "type": "Point"}, "id": 227, "properties": {"WIDTH_UNITS": null, "LENGTH": null, "FACILITY_CLASS": 3, "DESCRIPTION": "EWF;1 Youth Playscape(Roof);1 Tot/Youth Swing(3 Bays, 2 Buckets, 4 Belts)", "PRORAGIS_ID": "1571", "YEAR_BUILT": null, "STREET_NUMBER": "8601", "STATUS": "Open", "FACILITY_ID": "1401", "LWCF_PROTECTION": " ", "LONGITUDE": -97.83210976, "CREATED_BY": "hardya", "CITY_MUNICIPAL": "Austin", "PROTECTION_COMMENTS": null, "YEAR_OPEN": null, "STREET_NAME": "Piney Creek", "MANAGING_AGENCY_NAME": "City of Austin Parks and Recreation", "ASSET_MGMT_ID": 246.1401, "SIZE_UNITS": null, "MODIFIED_BY": "hardya", "LENGTH_UNITS": null, "ACCESSIBILITY_STATUS": "Accessible", "STATE": "TX", "FACILITY_TYPE": "Playground", "ADDRESS": "8601 Piney Creek Bnd., Austin, Texas 78745", "RESERVATIONS": "No", "ZIP_CODE": "78745", "PARK_ID": "246", "COUNTY": "Travis", "PARD_ID_1": 246, "OTHER_PROTECTIONS": " ", "OBJECTID": 227, "FACILITYOWNER_TYPE": "Municipal", "STREET_TYPE": "Bnd.", "CREATED_DATE": 1359504000000, "LATITUDE": 30.19389549, "WIDTH": null, "FACILITY_NAME": "Piney Bend Neighborhood Park Playground", "MANAGINGAGENCY_TYPE": "Municipal", "FACILITY_OWNER_NAME": "City of Austin Parks and Recreation", "INDOOR_OUTDOOR": "Outdoor", "MODIFIED_DATE": 1392379649000, "FACILITY_SIZE": null}, "type": "Feature"}], "type": "FeatureCollection"}