{"features": [{"properties": {"PARD_ID_1": 186, "COUNTY": "Travis", "MODIFIED_BY": "hardya", "INDOOR_OUTDOOR": "Outdoor", "RESERVATIONS": "No", "PROTECTION_COMMENTS": null, "LWCF_PROTECTION": " ", "WIDTH": null, "FACILITY_OWNER_NAME": "City of Austin Parks and Recreation", "MANAGINGAGENCY_TYPE": "Municipal", "FACILITY_TYPE": "Playground", "OTHER_PROTECTIONS": " ", "FACILITY_NAME": "Kendra Page Neighborhood Park Tot Playground", "LENGTH_UNITS": null, "LATITUDE": 30.18108902, "ASSET_MGMT_ID": 186.1401, "STATUS": "Open", "YEAR_BUILT": null, "FACILITY_SIZE": null, "LONGITUDE": -97.76439722, "MODIFIED_DATE": 1392305015000, "CITY_MUNICIPAL": "Austin", "MANAGING_AGENCY_NAME": "City of Austin Parks and Recreation", "FACILITY_ID": "1401", "SIZE_UNITS": null, "DESCRIPTION": "Peagravel/PIP;1 Tot Playscape(Tree Canopy)", "ADDRESS": "2203 Blue Meadow Dr., Austin, Texas 78744", "WIDTH_UNITS": null, "ACCESSIBILITY_STATUS": "Accessible", "STREET_NUMBER": "2203", "ZIP_CODE": "78744", "YEAR_OPEN": null, "PARK_ID": "186", "FACILITY_CLASS": 3, "CREATED_DATE": 1359331200000, "CREATED_BY": "hardya", "STREET_NAME": "Blue Meadow", "STREET_TYPE": "Dr.", "PRORAGIS_ID": "1008", "OBJECTID": 2077, "STATE": "TX", "FACILITYOWNER_TYPE": "Municipal", "LENGTH": null}, "id": 2077, "geometry": {"coordinates": [-97.7643972174611, 30.1810890228019], "type": "Point"}, "type": "Feature"}, {"properties": {"PARD_ID_1": 186, "COUNTY": "Travis", "MODIFIED_BY": "hardya", "INDOOR_OUTDOOR": "Outdoor", "RESERVATIONS": "No", "PROTECTION_COMMENTS": null, "LWCF_PROTECTION": " ", "WIDTH": null, "FACILITY_OWNER_NAME": "City of Austin Parks and Recreation", "MANAGINGAGENCY_TYPE": "Municipal", "FACILITY_TYPE": "Volleyball", "OTHER_PROTECTIONS": " ", "FACILITY_NAME": "Kendra Page Neighborhood Park Volleyball Court", "LENGTH_UNITS": null, "LATITUDE": 30.1808665, "ASSET_MGMT_ID": 186.301, "STATUS": "Open", "YEAR_BUILT": null, "FACILITY_SIZE": null, "LONGITUDE": -97.76446806, "MODIFIED_DATE": 1392305017000, "CITY_MUNICIPAL": "Austin", "MANAGING_AGENCY_NAME": "City of Austin Parks and Recreation", "FACILITY_ID": "301", "SIZE_UNITS": null, "DESCRIPTION": "Sand Court; No Lights", "ADDRESS": "2203 Blue Meadow Dr., Austin, Texas 78744", "WIDTH_UNITS": null, "ACCESSIBILITY_STATUS": "Not Accessible", "STREET_NUMBER": "2203", "ZIP_CODE": "78744", "YEAR_OPEN": null, "PARK_ID": "186", "FACILITY_CLASS": 8, "CREATED_DATE": 1352419200000, "CREATED_BY": "hardya", "STREET_NAME": "Blue Meadow", "STREET_TYPE": "Dr.", "PRORAGIS_ID": "1009", "OBJECTID": 2078, "STATE": "TX", "FACILITYOWNER_TYPE": "Municipal", "LENGTH": null}, "id": 2078, "geometry": {"coordinates": [-97.7644680594102, 30.1808664957989], "type": "Point"}, "type": "Feature"}, {"properties": {"PARD_ID_1": 186, "COUNTY": "Travis", "MODIFIED_BY": "hardya", "INDOOR_OUTDOOR": "Outdoor", "RESERVATIONS": "No", "PROTECTION_COMMENTS": null, "LWCF_PROTECTION": " ", "WIDTH": null, "FACILITY_OWNER_NAME": "City of Austin Parks and Recreation", "MANAGINGAGENCY_TYPE": "Municipal", "FACILITY_TYPE": "Playground", "OTHER_PROTECTIONS": " ", "FACILITY_NAME": "Kendra Page Neighborhood Park Youth Playground", "LENGTH_UNITS": null, "LATITUDE": 30.18112415, "ASSET_MGMT_ID": 186.1402, "STATUS": "Open", "YEAR_BUILT": null, "FACILITY_SIZE": null, "LONGITUDE": -97.76458871, "MODIFIED_DATE": 1392305022000, "CITY_MUNICIPAL": "Austin", "MANAGING_AGENCY_NAME": "City of Austin Parks and Recreation", "FACILITY_ID": "1402", "SIZE_UNITS": null, "DESCRIPTION": "Peagravel/PIP;1 Youth Playscape(Tree Canopy)", "ADDRESS": "2203 Blue Meadow Dr., Austin, Texas 78744", "WIDTH_UNITS": null, "ACCESSIBILITY_STATUS": "Accessible", "STREET_NUMBER": "2203", "ZIP_CODE": "78744", "YEAR_OPEN": null, "PARK_ID": "186", "FACILITY_CLASS": 3, "CREATED_DATE": 1359331200000, "CREATED_BY": "hardya", "STREET_NAME": "Blue Meadow", "STREET_TYPE": "Dr.", "PRORAGIS_ID": "1010", "OBJECTID": 2079, "STATE": "TX", "FACILITYOWNER_TYPE": "Municipal", "LENGTH": null}, "id": 2079, "geometry": {"coordinates": [-97.7645887073297, 30.1811241517929], "type": "Point"}, "type": "Feature"}], "type": "FeatureCollection"}