{"type": "FeatureCollection", "features": [{"properties": {"ACCESSIBILITY_STATUS": "Accessible", "PARK_ID": "186", "STREET_NUMBER": "2203", "WIDTH": null, "LONGITUDE": -97.76439722, "YEAR_BUILT": null, "PARD_ID_1": 186, "CREATED_BY": "hardya", "FACILITY_TYPE": "Playground", "OTHER_PROTECTIONS": " ", "ZIP_CODE": "78744", "MODIFIED_BY": "hardya", "PRORAGIS_ID": "1008", "PROTECTION_COMMENTS": null, "RESERVATIONS": "No", "ASSET_MGMT_ID": 186.1401, "COUNTY": "Travis", "CREATED_DATE": 1359331200000, "STATE": "TX", "SIZE_UNITS": null, "MODIFIED_DATE": 1392305015000, "FACILITY_SIZE": null, "FACILITY_OWNER_NAME": "City of Austin Parks and Recreation", "INDOOR_OUTDOOR": "Outdoor", "FACILITY_NAME": "Kendra Page Neighborhood Park Tot Playground", "LWCF_PROTECTION": " ", "CITY_MUNICIPAL": "Austin", "LATITUDE": 30.18108902, "WIDTH_UNITS": null, "FACILITY_ID": "1401", "STREET_TYPE": "Dr.", "STREET_NAME": "Blue Meadow", "LENGTH": null, "MANAGINGAGENCY_TYPE": "Municipal", "DESCRIPTION": "Peagravel/PIP;1 Tot Playscape(Tree Canopy)", "OBJECTID": 2077, "FACILITYOWNER_TYPE": "Municipal", "STATUS": "Open", "YEAR_OPEN": null, "MANAGING_AGENCY_NAME": "City of Austin Parks and Recreation", "ADDRESS": "2203 Blue Meadow Dr., Austin, Texas 78744", "LENGTH_UNITS": null, "FACILITY_CLASS": 3}, "type": "Feature", "geometry": {"type": "Point", "coordinates": [-97.7643972174611, 30.1810890228019]}, "id": 2077}, {"properties": {"ACCESSIBILITY_STATUS": "Not Accessible", "PARK_ID": "186", "STREET_NUMBER": "2203", "WIDTH": null, "LONGITUDE": -97.76446806, "YEAR_BUILT": null, "PARD_ID_1": 186, "CREATED_BY": "hardya", "FACILITY_TYPE": "Volleyball", "OTHER_PROTECTIONS": " ", "ZIP_CODE": "78744", "MODIFIED_BY": "hardya", "PRORAGIS_ID": "1009", "PROTECTION_COMMENTS": null, "RESERVATIONS": "No", "ASSET_MGMT_ID": 186.301, "COUNTY": "Travis", "CREATED_DATE": 1352419200000, "STATE": "TX", "SIZE_UNITS": null, "MODIFIED_DATE": 1392305017000, "FACILITY_SIZE": null, "FACILITY_OWNER_NAME": "City of Austin Parks and Recreation", "INDOOR_OUTDOOR": "Outdoor", "FACILITY_NAME": "Kendra Page Neighborhood Park Volleyball Court", "LWCF_PROTECTION": " ", "CITY_MUNICIPAL": "Austin", "LATITUDE": 30.1808665, "WIDTH_UNITS": null, "FACILITY_ID": "301", "STREET_TYPE": "Dr.", "STREET_NAME": "Blue Meadow", "LENGTH": null, "MANAGINGAGENCY_TYPE": "Municipal", "DESCRIPTION": "Sand Court; No Lights", "OBJECTID": 2078, "FACILITYOWNER_TYPE": "Municipal", "STATUS": "Open", "YEAR_OPEN": null, "MANAGING_AGENCY_NAME": "City of Austin Parks and Recreation", "ADDRESS": "2203 Blue Meadow Dr., Austin, Texas 78744", "LENGTH_UNITS": null, "FACILITY_CLASS": 8}, "type": "Feature", "geometry": {"type": "Point", "coordinates": [-97.7644680594102, 30.1808664957989]}, "id": 2078}, {"properties": {"ACCESSIBILITY_STATUS": "Accessible", "PARK_ID": "186", "STREET_NUMBER": "2203", "WIDTH": null, "LONGITUDE": -97.76458871, "YEAR_BUILT": null, "PARD_ID_1": 186, "CREATED_BY": "hardya", "FACILITY_TYPE": "Playground", "OTHER_PROTECTIONS": " ", "ZIP_CODE": "78744", "MODIFIED_BY": "hardya", "PRORAGIS_ID": "1010", "PROTECTION_COMMENTS": null, "RESERVATIONS": "No", "ASSET_MGMT_ID": 186.1402, "COUNTY": "Travis", "CREATED_DATE": 1359331200000, "STATE": "TX", "SIZE_UNITS": null, "MODIFIED_DATE": 1392305022000, "FACILITY_SIZE": null, "FACILITY_OWNER_NAME": "City of Austin Parks and Recreation", "INDOOR_OUTDOOR": "Outdoor", "FACILITY_NAME": "Kendra Page Neighborhood Park Youth Playground", "LWCF_PROTECTION": " ", "CITY_MUNICIPAL": "Austin", "LATITUDE": 30.18112415, "WIDTH_UNITS": null, "FACILITY_ID": "1402", "STREET_TYPE": "Dr.", "STREET_NAME": "Blue Meadow", "LENGTH": null, "MANAGINGAGENCY_TYPE": "Municipal", "DESCRIPTION": "Peagravel/PIP;1 Youth Playscape(Tree Canopy)", "OBJECTID": 2079, "FACILITYOWNER_TYPE": "Municipal", "STATUS": "Open", "YEAR_OPEN": null, "MANAGING_AGENCY_NAME": "City of Austin Parks and Recreation", "ADDRESS": "2203 Blue Meadow Dr., Austin, Texas 78744", "LENGTH_UNITS": null, "FACILITY_CLASS": 3}, "type": "Feature", "geometry": {"type": "Point", "coordinates": [-97.7645887073297, 30.1811241517929]}, "id": 2079}]}