{"features": [{"properties": {"PARD_ID_1": 246, "COUNTY": "Travis", "MODIFIED_BY": "hardya", "INDOOR_OUTDOOR": "Outdoor", "RESERVATIONS": "No", "PROTECTION_COMMENTS": null, "LWCF_PROTECTION": " ", "WIDTH": null, "FACILITY_OWNER_NAME": "City of Austin Parks and Recreation", "MANAGINGAGENCY_TYPE": "Municipal", "FACILITY_TYPE": "Playground", "OTHER_PROTECTIONS": " ", "FACILITY_NAME": "Piney Bend Neighborhood Park Playground", "LENGTH_UNITS": null, "LATITUDE": 30.19389549, "ASSET_MGMT_ID": 246.1401, "STATUS": "Open", "YEAR_BUILT": null, "FACILITY_SIZE": null, "LONGITUDE": -97.83210976, "MODIFIED_DATE": 1392379649000, "CITY_MUNICIPAL": "Austin", "MANAGING_AGENCY_NAME": "City of Austin Parks and Recreation", "FACILITY_ID": "1401", "SIZE_UNITS": null, "DESCRIPTION": "EWF;1 Youth Playscape(Roof);1 Tot/Youth Swing(3 Bays, 2 Buckets, 4 Belts)", "ADDRESS": "8601 Piney Creek Bnd., Austin, Texas 78745", "WIDTH_UNITS": null, "ACCESSIBILITY_STATUS": "Accessible", "STREET_NUMBER": "8601", "ZIP_CODE": "78745", "YEAR_OPEN": null, "PARK_ID": "246", "FACILITY_CLASS": 3, "CREATED_DATE": 1359504000000, "CREATED_BY": "hardya", "STREET_NAME": "Piney Creek", "STREET_TYPE": "Bnd.", "PRORAGIS_ID": "1571", "OBJECTID": 227, "STATE": "TX", "FACILITYOWNER_TYPE": "Municipal", "LENGTH": null}, "id": 227, "geometry": {"coordinates": [-97.8321097561376, 30.1938954854767], "type": "Point"}, "type": "Feature"}], "type": "FeatureCollection"}