{"features": [{"properties": {"PARD_ID_1": 319, "COUNTY": "Travis", "MODIFIED_BY": "roosg", "INDOOR_OUTDOOR": "Outdoor", "RESERVATIONS": "No", "PROTECTION_COMMENTS": null, "LWCF_PROTECTION": " ", "WIDTH": null, "FACILITY_OWNER_NAME": "City of Austin", "MANAGINGAGENCY_TYPE": "Municipal", "FACILITY_TYPE": "Memorial", "OTHER_PROTECTIONS": " ", "FACILITY_NAME": "Wooldridge Square: Gift of Austin Newcomers Club Memorial Bench", "LENGTH_UNITS": null, "LATITUDE": 30.27278899, "ASSET_MGMT_ID": 319.1003, "STATUS": "Open", "YEAR_BUILT": null, "FACILITY_SIZE": null, "LONGITUDE": -97.74583481, "MODIFIED_DATE": 1427883586000, "CITY_MUNICIPAL": "Austin", "MANAGING_AGENCY_NAME": "City of Austin Parks and Recreation", "FACILITY_ID": "1003", "SIZE_UNITS": null, "DESCRIPTION": "1 Metal Bench", "ADDRESS": "900 Guadalupe St., Austin, Texas 78701", "WIDTH_UNITS": null, "ACCESSIBILITY_STATUS": "Accessible", "STREET_NUMBER": "900", "ZIP_CODE": "78701", "YEAR_OPEN": null, "PARK_ID": "319", "FACILITY_CLASS": 11, "CREATED_DATE": 1395065891000, "CREATED_BY": "hardya", "STREET_NAME": "Guadalupe", "STREET_TYPE": "St.", "PRORAGIS_ID": "3352", "OBJECTID": 88, "STATE": "TX", "FACILITYOWNER_TYPE": "Municipal", "LENGTH": null}, "id": 88, "geometry": {"coordinates": [-97.7458348054309, 30.2727889868446], "type": "Point"}, "type": "Feature"}, {"properties": {"PARD_ID_1": 319, "COUNTY": "Travis", "MODIFIED_BY": "hardya", "INDOOR_OUTDOOR": "Outdoor", "RESERVATIONS": "No", "PROTECTION_COMMENTS": null, "LWCF_PROTECTION": " ", "WIDTH": null, "FACILITY_OWNER_NAME": "City of Austin Parks and Recreation", "MANAGINGAGENCY_TYPE": "Municipal", "FACILITY_TYPE": "Gazebo", "OTHER_PROTECTIONS": " ", "FACILITY_NAME": "Wooldridge Square Gazebo", "LENGTH_UNITS": null, "LATITUDE": 30.27234368, "ASSET_MGMT_ID": 319.1601, "STATUS": "Open", "YEAR_BUILT": null, "FACILITY_SIZE": 400, "LONGITUDE": -97.74556776, "MODIFIED_DATE": 1392381276000, "CITY_MUNICIPAL": "Austin", "MANAGING_AGENCY_NAME": "City of Austin Parks and Recreation", "FACILITY_ID": "1601", "SIZE_UNITS": "Square Feet", "DESCRIPTION": "Trellis/Open Roof; No Benches", "ADDRESS": "900 Guadalupe St., Austin, Texas 78701", "WIDTH_UNITS": null, "ACCESSIBILITY_STATUS": "Not Accessible", "STREET_NUMBER": "900", "ZIP_CODE": "78701", "YEAR_OPEN": null, "PARK_ID": "319", "FACILITY_CLASS": 16, "CREATED_DATE": 1352366393000, "CREATED_BY": "hardya", "STREET_NAME": "Guadalupe", "STREET_TYPE": "St.", "PRORAGIS_ID": "2123", "OBJECTID": 795, "STATE": "TX", "FACILITYOWNER_TYPE": "Municipal", "LENGTH": null}, "id": 795, "geometry": {"coordinates": [-97.7455677552299, 30.2723436847366], "type": "Point"}, "type": "Feature"}], "type": "FeatureCollection"}