{"features": [{"properties": {"PARD_ID_1": 229, "COUNTY": "Travis", "MODIFIED_BY": "hardya", "INDOOR_OUTDOOR": "Outdoor", "RESERVATIONS": "No", "PROTECTION_COMMENTS": null, "LWCF_PROTECTION": " ", "WIDTH": null, "FACILITY_OWNER_NAME": "City of Austin Parks and Recreation", "MANAGINGAGENCY_TYPE": "Municipal", "FACILITY_TYPE": "Basketball", "OTHER_PROTECTIONS": " ", "FACILITY_NAME": "Stoney Ridge Neighborhood Park Basketball Court", "LENGTH_UNITS": null, "LATITUDE": 30.15793252, "ASSET_MGMT_ID": 229.301, "STATUS": "Open", "YEAR_BUILT": null, "FACILITY_SIZE": null, "LONGITUDE": -97.65140077, "MODIFIED_DATE": 1392380751000, "CITY_MUNICIPAL": "Austin LTD", "MANAGING_AGENCY_NAME": "City of Austin Parks and Recreation", "FACILITY_ID": "301", "SIZE_UNITS": null, "DESCRIPTION": "Full Court; Not Sheltered; 2 Goals", "ADDRESS": "7000 Moores Crossing Blvd., Austin, Texas 78617", "WIDTH_UNITS": null, "ACCESSIBILITY_STATUS": "Accessible", "STREET_NUMBER": "7000", "ZIP_CODE": "78617", "YEAR_OPEN": null, "PARK_ID": "229", "FACILITY_CLASS": 8, "CREATED_DATE": 1304899200000, "CREATED_BY": "hardya", "STREET_NAME": "Moores Crossing", "STREET_TYPE": "Blvd.", "PRORAGIS_ID": "1942", "OBJECTID": 379, "STATE": "TX", "FACILITYOWNER_TYPE": "Municipal", "LENGTH": null}, "id": 379, "geometry": {"coordinates": [-97.6514007734919, 30.1579325194959], "type": "Point"}, "type": "Feature"}, {"properties": {"PARD_ID_1": 229, "COUNTY": "Travis", "MODIFIED_BY": "hardya", "INDOOR_OUTDOOR": "Outdoor", "RESERVATIONS": "No", "PROTECTION_COMMENTS": null, "LWCF_PROTECTION": " ", "WIDTH": null, "FACILITY_OWNER_NAME": "City of Austin Parks and Recreation", "MANAGINGAGENCY_TYPE": "Municipal", "FACILITY_TYPE": "Parking Lot", "OTHER_PROTECTIONS": " ", "FACILITY_NAME": "Stoney Ridge Neighborhood Park Parking Lot", "LENGTH_UNITS": null, "LATITUDE": 30.1584085, "ASSET_MGMT_ID": 229.2001, "STATUS": "Open", "YEAR_BUILT": null, "FACILITY_SIZE": null, "LONGITUDE": -97.65208037, "MODIFIED_DATE": 1392380753000, "CITY_MUNICIPAL": "Austin LTD", "MANAGING_AGENCY_NAME": "City of Austin Parks and Recreation", "FACILITY_ID": "2001", "SIZE_UNITS": null, "DESCRIPTION": "Concrete; 7 Regular Spaces/ 0 ADA Spaces", "ADDRESS": "7000 Moores Crossing Blvd., Austin, Texas 78617", "WIDTH_UNITS": null, "ACCESSIBILITY_STATUS": "Not Accessible", "STREET_NUMBER": "7000", "ZIP_CODE": "78617", "YEAR_OPEN": null, "PARK_ID": "229", "FACILITY_CLASS": 20, "CREATED_DATE": 1286323200000, "CREATED_BY": "hardya", "STREET_NAME": "Moores Crossing", "STREET_TYPE": "Blvd.", "PRORAGIS_ID": "1943", "OBJECTID": 380, "STATE": "TX", "FACILITYOWNER_TYPE": "Municipal", "LENGTH": null}, "id": 380, "geometry": {"coordinates": [-97.6520803710388, 30.1584085020557], "type": "Point"}, "type": "Feature"}, {"properties": {"PARD_ID_1": 229, "COUNTY": "Travis", "MODIFIED_BY": "hardya", "INDOOR_OUTDOOR": "Outdoor", "RESERVATIONS": "No", "PROTECTION_COMMENTS": null, "LWCF_PROTECTION": " ", "WIDTH": null, "FACILITY_OWNER_NAME": "City of Austin Parks and Recreation", "MANAGINGAGENCY_TYPE": "Municipal", "FACILITY_TYPE": "Playground", "OTHER_PROTECTIONS": " ", "FACILITY_NAME": "Stoney Ridge Neighborhood Park Playground", "LENGTH_UNITS": null, "LATITUDE": 30.15815771, "ASSET_MGMT_ID": 229.1401, "STATUS": "Open", "YEAR_BUILT": null, "FACILITY_SIZE": null, "LONGITUDE": -97.65177212, "MODIFIED_DATE": 1392395572000, "CITY_MUNICIPAL": "Austin LTD", "MANAGING_AGENCY_NAME": "City of Austin Parks and Recreation", "FACILITY_ID": "1401", "SIZE_UNITS": null, "DESCRIPTION": "SRM;1 Youth Playscape(Roof)", "ADDRESS": "7000 Moores Crossing Blvd., Austin, Texas 78617", "WIDTH_UNITS": null, "ACCESSIBILITY_STATUS": "Not Accessible", "STREET_NUMBER": "7000", "ZIP_CODE": "78617", "YEAR_OPEN": null, "PARK_ID": "229", "FACILITY_CLASS": 3, "CREATED_DATE": 1359331200000, "CREATED_BY": "hardya", "STREET_NAME": "Moores Crossing", "STREET_TYPE": "Blvd.", "PRORAGIS_ID": "2305", "OBJECTID": 1045, "STATE": "TX", "FACILITYOWNER_TYPE": "Municipal", "LENGTH": null}, "id": 1045, "geometry": {"coordinates": [-97.6517721199982, 30.1581577118731], "type": "Point"}, "type": "Feature"}], "type": "FeatureCollection"}