{"features": [{"geometry": {"coordinates": [-97.6514007734919, 30.1579325194959], "type": "Point"}, "id": 379, "properties": {"WIDTH_UNITS": null, "LENGTH": null, "FACILITY_CLASS": 8, "DESCRIPTION": "Full Court; Not Sheltered; 2 Goals", "PRORAGIS_ID": "1942", "YEAR_BUILT": null, "STREET_NUMBER": "7000", "STATUS": "Open", "FACILITY_ID": "301", "LWCF_PROTECTION": " ", "LONGITUDE": -97.65140077, "CREATED_BY": "hardya", "CITY_MUNICIPAL": "Austin LTD", "PROTECTION_COMMENTS": null, "YEAR_OPEN": null, "STREET_NAME": "Moores Crossing", "MANAGING_AGENCY_NAME": "City of Austin Parks and Recreation", "ASSET_MGMT_ID": 229.301, "SIZE_UNITS": null, "MODIFIED_BY": "hardya", "LENGTH_UNITS": null, "ACCESSIBILITY_STATUS": "Accessible", "STATE": "TX", "FACILITY_TYPE": "Basketball", "ADDRESS": "7000 Moores Crossing Blvd., Austin, Texas 78617", "RESERVATIONS": "No", "ZIP_CODE": "78617", "PARK_ID": "229", "COUNTY": "Travis", "PARD_ID_1": 229, "OTHER_PROTECTIONS": " ", "OBJECTID": 379, "FACILITYOWNER_TYPE": "Municipal", "STREET_TYPE": "Blvd.", "CREATED_DATE": 1304899200000, "LATITUDE": 30.15793252, "WIDTH": null, "FACILITY_NAME": "Stoney Ridge Neighborhood Park Basketball Court", "MANAGINGAGENCY_TYPE": "Municipal", "FACILITY_OWNER_NAME": "City of Austin Parks and Recreation", "INDOOR_OUTDOOR": "Outdoor", "MODIFIED_DATE": 1392380751000, "FACILITY_SIZE": null}, "type": "Feature"}, {"geometry": {"coordinates": [-97.6520803710388, 30.1584085020557], "type": "Point"}, "id": 380, "properties": {"WIDTH_UNITS": null, "LENGTH": null, "FACILITY_CLASS": 20, "DESCRIPTION": "Concrete; 7 Regular Spaces/ 0 ADA Spaces", "PRORAGIS_ID": "1943", "YEAR_BUILT": null, "STREET_NUMBER": "7000", "STATUS": "Open", "FACILITY_ID": "2001", "LWCF_PROTECTION": " ", "LONGITUDE": -97.65208037, "CREATED_BY": "hardya", "CITY_MUNICIPAL": "Austin LTD", "PROTECTION_COMMENTS": null, "YEAR_OPEN": null, "STREET_NAME": "Moores Crossing", "MANAGING_AGENCY_NAME": "City of Austin Parks and Recreation", "ASSET_MGMT_ID": 229.2001, "SIZE_UNITS": null, "MODIFIED_BY": "hardya", "LENGTH_UNITS": null, "ACCESSIBILITY_STATUS": "Not Accessible", "STATE": "TX", "FACILITY_TYPE": "Parking Lot", "ADDRESS": "7000 Moores Crossing Blvd., Austin, Texas 78617", "RESERVATIONS": "No", "ZIP_CODE": "78617", "PARK_ID": "229", "COUNTY": "Travis", "PARD_ID_1": 229, "OTHER_PROTECTIONS": " ", "OBJECTID": 380, "FACILITYOWNER_TYPE": "Municipal", "STREET_TYPE": "Blvd.", "CREATED_DATE": 1286323200000, "LATITUDE": 30.1584085, "WIDTH": null, "FACILITY_NAME": "Stoney Ridge Neighborhood Park Parking Lot", "MANAGINGAGENCY_TYPE": "Municipal", "FACILITY_OWNER_NAME": "City of Austin Parks and Recreation", "INDOOR_OUTDOOR": "Outdoor", "MODIFIED_DATE": 1392380753000, "FACILITY_SIZE": null}, "type": "Feature"}, {"geometry": {"coordinates": [-97.6517721199982, 30.1581577118731], "type": "Point"}, "id": 1045, "properties": {"WIDTH_UNITS": null, "LENGTH": null, "FACILITY_CLASS": 3, "DESCRIPTION": "SRM;1 Youth Playscape(Roof)", "PRORAGIS_ID": "2305", "YEAR_BUILT": null, "STREET_NUMBER": "7000", "STATUS": "Open", "FACILITY_ID": "1401", "LWCF_PROTECTION": " ", "LONGITUDE": -97.65177212, "CREATED_BY": "hardya", "CITY_MUNICIPAL": "Austin LTD", "PROTECTION_COMMENTS": null, "YEAR_OPEN": null, "STREET_NAME": "Moores Crossing", "MANAGING_AGENCY_NAME": "City of Austin Parks and Recreation", "ASSET_MGMT_ID": 229.1401, "SIZE_UNITS": null, "MODIFIED_BY": "hardya", "LENGTH_UNITS": null, "ACCESSIBILITY_STATUS": "Not Accessible", "STATE": "TX", "FACILITY_TYPE": "Playground", "ADDRESS": "7000 Moores Crossing Blvd., Austin, Texas 78617", "RESERVATIONS": "No", "ZIP_CODE": "78617", "PARK_ID": "229", "COUNTY": "Travis", "PARD_ID_1": 229, "OTHER_PROTECTIONS": " ", "OBJECTID": 1045, "FACILITYOWNER_TYPE": "Municipal", "STREET_TYPE": "Blvd.", "CREATED_DATE": 1359331200000, "LATITUDE": 30.15815771, "WIDTH": null, "FACILITY_NAME": "Stoney Ridge Neighborhood Park Playground", "MANAGINGAGENCY_TYPE": "Municipal", "FACILITY_OWNER_NAME": "City of Austin Parks and Recreation", "INDOOR_OUTDOOR": "Outdoor", "MODIFIED_DATE": 1392395572000, "FACILITY_SIZE": null}, "type": "Feature"}], "type": "FeatureCollection"}