{"features": [{"properties": {"PARD_ID_1": 224, "COUNTY": "Travis", "MODIFIED_BY": "hardya", "INDOOR_OUTDOOR": "Outdoor", "RESERVATIONS": "No", "PROTECTION_COMMENTS": null, "LWCF_PROTECTION": " ", "WIDTH": null, "FACILITY_OWNER_NAME": "Austin Independent School District", "MANAGINGAGENCY_TYPE": "Municipal", "FACILITY_TYPE": "Basketball", "OTHER_PROTECTIONS": " ", "FACILITY_NAME": "Oak Springs School Park Basketball Court", "LENGTH_UNITS": null, "LATITUDE": 30.27169187, "ASSET_MGMT_ID": 224.301, "STATUS": "Open_Restricted", "YEAR_BUILT": null, "FACILITY_SIZE": null, "LONGITUDE": -97.70359989, "MODIFIED_DATE": 1392379250000, "CITY_MUNICIPAL": "Austin", "MANAGING_AGENCY_NAME": "City of Austin Parks and Recreation", "FACILITY_ID": "301", "SIZE_UNITS": null, "DESCRIPTION": "Full Court; Sheltered with ShadeCloth; 2 Goals", "ADDRESS": "2806 Goodwin Ave., Austin, Texas 78702", "WIDTH_UNITS": null, "ACCESSIBILITY_STATUS": "Not Accessible", "STREET_NUMBER": "2806", "ZIP_CODE": "78702", "YEAR_OPEN": null, "PARK_ID": "224", "FACILITY_CLASS": 8, "CREATED_DATE": 1026950400000, "CREATED_BY": "<Null>", "STREET_NAME": "Goodwin", "STREET_TYPE": "Ave.", "PRORAGIS_ID": "1452", "OBJECTID": 16, "STATE": "TX", "FACILITYOWNER_TYPE": "School", "LENGTH": null}, "id": 16, "geometry": {"coordinates": [-97.7035998884451, 30.2716918712024], "type": "Point"}, "type": "Feature"}, {"properties": {"PARD_ID_1": 224, "COUNTY": "Travis", "MODIFIED_BY": "hardya", "INDOOR_OUTDOOR": "Outdoor", "RESERVATIONS": "No", "PROTECTION_COMMENTS": null, "LWCF_PROTECTION": " ", "WIDTH": null, "FACILITY_OWNER_NAME": "Austin Independent School District", "MANAGINGAGENCY_TYPE": "School", "FACILITY_TYPE": "Parking Lot", "OTHER_PROTECTIONS": " ", "FACILITY_NAME": "Oak Springs School Park Parking Lot", "LENGTH_UNITS": null, "LATITUDE": 30.2711371, "ASSET_MGMT_ID": 224.2001, "STATUS": "Open_Restricted", "YEAR_BUILT": null, "FACILITY_SIZE": null, "LONGITUDE": -97.70445219, "MODIFIED_DATE": 1392379254000, "CITY_MUNICIPAL": "Austin", "MANAGING_AGENCY_NAME": "Austin Independent School District", "FACILITY_ID": "2001", "SIZE_UNITS": null, "DESCRIPTION": "Concrete; 20 Regular Spaces/ 2 ADA Spaces/ School Parking", "ADDRESS": "2806 Goodwin Ave., Austin, Texas 78702", "WIDTH_UNITS": null, "ACCESSIBILITY_STATUS": "Accessible", "STREET_NUMBER": "2806", "ZIP_CODE": "78702", "YEAR_OPEN": null, "PARK_ID": "224", "FACILITY_CLASS": 20, "CREATED_DATE": 1026950400000, "CREATED_BY": "<Null>", "STREET_NAME": "Goodwin", "STREET_TYPE": "Ave.", "PRORAGIS_ID": "1454", "OBJECTID": 17, "STATE": "TX", "FACILITYOWNER_TYPE": "School", "LENGTH": null}, "id": 17, "geometry": {"coordinates": [-97.7044521860091, 30.2711371048757], "type": "Point"}, "type": "Feature"}, {"properties": {"PARD_ID_1": 224, "COUNTY": "Travis", "MODIFIED_BY": "hardya", "INDOOR_OUTDOOR": "Outdoor", "RESERVATIONS": "Yes", "PROTECTION_COMMENTS": null, "LWCF_PROTECTION": " ", "WIDTH": null, "FACILITY_OWNER_NAME": "Austin Independent School District", "MANAGINGAGENCY_TYPE": "Municipal", "FACILITY_TYPE": "Mixed Use Field", "OTHER_PROTECTIONS": " ", "FACILITY_NAME": "Oak Springs School Park Mixed Use Field", "LENGTH_UNITS": null, "LATITUDE": 30.27211691, "ASSET_MGMT_ID": 224.1901, "STATUS": "Open_Restricted", "YEAR_BUILT": null, "FACILITY_SIZE": null, "LONGITUDE": -97.70316186, "MODIFIED_DATE": 1398089599000, "CITY_MUNICIPAL": "Austin", "MANAGING_AGENCY_NAME": "City of Austin Parks and Recreation", "FACILITY_ID": "1901", "SIZE_UNITS": null, "DESCRIPTION": "No Backstop; No Goals; No Lights; No Stands; No Scoreboard", "ADDRESS": "2806 Goodwin Ave., Austin, Texas 78702", "WIDTH_UNITS": null, "ACCESSIBILITY_STATUS": "Not Accessible", "STREET_NUMBER": "2806", "ZIP_CODE": "78702", "YEAR_OPEN": null, "PARK_ID": "224", "FACILITY_CLASS": 10, "CREATED_DATE": 1199145600000, "CREATED_BY": "hardya", "STREET_NAME": "Goodwin", "STREET_TYPE": "Ave.", "PRORAGIS_ID": "1453", "OBJECTID": 1416, "STATE": "TX", "FACILITYOWNER_TYPE": "School", "LENGTH": null}, "id": 1416, "geometry": {"coordinates": [-97.7031618637322, 30.272116905368], "type": "Point"}, "type": "Feature"}], "type": "FeatureCollection"}