{"type": "FeatureCollection", "features": [{"properties": {"ACCESSIBILITY_STATUS": "Accessible", "PARK_ID": "328", "STREET_NUMBER": "2220", "WIDTH": null, "LONGITUDE": -97.72174724, "YEAR_BUILT": null, "PARD_ID_1": 328, "CREATED_BY": "hardya", "FACILITY_TYPE": "Visual Arts/Crafts", "OTHER_PROTECTIONS": " ", "ZIP_CODE": "78702", "MODIFIED_BY": "hardya", "PRORAGIS_ID": "3392", "PROTECTION_COMMENTS": null, "RESERVATIONS": "No", "ASSET_MGMT_ID": 328.1801, "COUNTY": "Travis", "CREATED_DATE": 1395222382000, "STATE": "TX", "SIZE_UNITS": null, "MODIFIED_DATE": 1408534071000, "FACILITY_SIZE": null, "FACILITY_OWNER_NAME": "City of Austin Parks and Recreation", "INDOOR_OUTDOOR": "Outdoor", "FACILITY_NAME": "Manuel and Robert Donley Pocket Park: Archway Installation", "LWCF_PROTECTION": " ", "CITY_MUNICIPAL": "Austin", "LATITUDE": 30.24987051, "WIDTH_UNITS": null, "FACILITY_ID": "1801", "STREET_TYPE": "St.", "STREET_NAME": "Riverview", "LENGTH": null, "MANAGINGAGENCY_TYPE": "Municipal", "DESCRIPTION": "Archway Installation", "OBJECTID": 1757, "FACILITYOWNER_TYPE": "Municipal", "STATUS": "Open", "YEAR_OPEN": null, "MANAGING_AGENCY_NAME": "City of Austin Parks and Recreation", "ADDRESS": "2220 Riverview St., Austin, Texas 78702", "LENGTH_UNITS": null, "FACILITY_CLASS": 9}, "type": "Feature", "geometry": {"type": "Point", "coordinates": [-97.721747236054, 30.2498705140313]}, "id": 1757}]}