{"features": [{"geometry": {"coordinates": [-97.7675184856076, 30.2138842950996], "type": "Point"}, "id": 1622, "properties": {"WIDTH_UNITS": null, "LENGTH": null, "FACILITY_CLASS": 8, "DESCRIPTION": "Full Court; Not Sheltered; 2 Goals", "PRORAGIS_ID": "184", "YEAR_BUILT": null, "STREET_NUMBER": "121", "STATUS": "Open", "FACILITY_ID": "301", "LWCF_PROTECTION": " ", "LONGITUDE": -97.76751849, "CREATED_BY": "<Null>", "CITY_MUNICIPAL": "Austin", "PROTECTION_COMMENTS": null, "YEAR_OPEN": null, "STREET_NAME": "Sheraton ", "MANAGING_AGENCY_NAME": "City of Austin Parks and Recreation", "ASSET_MGMT_ID": 117.301, "SIZE_UNITS": null, "MODIFIED_BY": "hardya", "LENGTH_UNITS": null, "ACCESSIBILITY_STATUS": "Not Accessible", "STATE": "TX", "FACILITY_TYPE": "Basketball", "ADDRESS": "121 Sheraton Ave., Austin, Texas 78745", "RESERVATIONS": "No", "ZIP_CODE": "78745", "PARK_ID": "117", "COUNTY": "Travis", "PARD_ID_1": 117, "OTHER_PROTECTIONS": " ", "OBJECTID": 1622, "FACILITYOWNER_TYPE": "Municipal", "STREET_TYPE": "Ave.", "CREATED_DATE": 1021507200000, "LATITUDE": 30.2138843, "WIDTH": null, "FACILITY_NAME": "Battle Bend Neighborhood Park Basketball Court", "MANAGINGAGENCY_TYPE": "Municipal", "FACILITY_OWNER_NAME": "City of Austin Parks and Recreation", "INDOOR_OUTDOOR": "Outdoor", "MODIFIED_DATE": 1392289054000, "FACILITY_SIZE": null}, "type": "Feature"}, {"geometry": {"coordinates": [-97.7676863454256, 30.214184735946], "type": "Point"}, "id": 1623, "properties": {"WIDTH_UNITS": null, "LENGTH": null, "FACILITY_CLASS": 16, "DESCRIPTION": "Covered Roof; 3 Benches", "PRORAGIS_ID": "185", "YEAR_BUILT": null, "STREET_NUMBER": "121", "STATUS": "Open", "FACILITY_ID": "1601", "LWCF_PROTECTION": " ", "LONGITUDE": -97.76768635, "CREATED_BY": "hardya", "CITY_MUNICIPAL": "Austin", "PROTECTION_COMMENTS": null, "YEAR_OPEN": null, "STREET_NAME": "Sheraton ", "MANAGING_AGENCY_NAME": "City of Austin Parks and Recreation", "ASSET_MGMT_ID": 117.1601, "SIZE_UNITS": "Square Feet", "MODIFIED_BY": "hardya", "LENGTH_UNITS": null, "ACCESSIBILITY_STATUS": "Not Accessible", "STATE": "TX", "FACILITY_TYPE": "Gazebo", "ADDRESS": "121 Sheraton Ave., Austin, Texas 78745", "RESERVATIONS": "No", "ZIP_CODE": "78745", "PARK_ID": "117", "COUNTY": "Travis", "PARD_ID_1": 117, "OTHER_PROTECTIONS": " ", "OBJECTID": 1623, "FACILITYOWNER_TYPE": "Municipal", "STREET_TYPE": "Ave.", "CREATED_DATE": 1352366398000, "LATITUDE": 30.21418474, "WIDTH": null, "FACILITY_NAME": "Battle Bend Neighborhood Park Gazebo", "MANAGINGAGENCY_TYPE": "Municipal", "FACILITY_OWNER_NAME": "City of Austin Parks and Recreation", "INDOOR_OUTDOOR": "Outdoor", "MODIFIED_DATE": 1392289056000, "FACILITY_SIZE": 400}, "type": "Feature"}, {"geometry": {"coordinates": [-97.7679143278681, 30.214167284523], "type": "Point"}, "id": 1624, "properties": {"WIDTH_UNITS": null, "LENGTH": null, "FACILITY_CLASS": 3, "DESCRIPTION": "Peagravel/PIP;1 Tot Playscape;1 Youth Playscape;1 Tot Swing(1 Bay, 2 Buckets)", "PRORAGIS_ID": "186", "YEAR_BUILT": null, "STREET_NUMBER": "121", "STATUS": "Open", "FACILITY_ID": "1401", "LWCF_PROTECTION": " ", "LONGITUDE": -97.76791433, "CREATED_BY": "hardya", "CITY_MUNICIPAL": "Austin", "PROTECTION_COMMENTS": null, "YEAR_OPEN": null, "STREET_NAME": "Sheraton ", "MANAGING_AGENCY_NAME": "City of Austin Parks and Recreation", "ASSET_MGMT_ID": 117.1401, "SIZE_UNITS": null, "MODIFIED_BY": "hardya", "LENGTH_UNITS": null, "ACCESSIBILITY_STATUS": "Accessible", "STATE": "TX", "FACILITY_TYPE": "Playground", "ADDRESS": "121 Sheraton Ave., Austin, Texas 78745", "RESERVATIONS": "No", "ZIP_CODE": "78745", "PARK_ID": "117", "COUNTY": "Travis", "PARD_ID_1": 117, "OTHER_PROTECTIONS": " ", "OBJECTID": 1624, "FACILITYOWNER_TYPE": "Municipal", "STREET_TYPE": "Ave.", "CREATED_DATE": 1359504000000, "LATITUDE": 30.21416728, "WIDTH": null, "FACILITY_NAME": "Battle Bend Neighborhood Park Playground", "MANAGINGAGENCY_TYPE": "Municipal", "FACILITY_OWNER_NAME": "City of Austin Parks and Recreation", "INDOOR_OUTDOOR": "Outdoor", "MODIFIED_DATE": 1392289058000, "FACILITY_SIZE": null}, "type": "Feature"}], "type": "FeatureCollection"}