{"features": [{"geometry": {"coordinates": [-97.7458348054309, 30.2727889868446], "type": "Point"}, "id": 88, "properties": {"WIDTH_UNITS": null, "LENGTH": null, "FACILITY_CLASS": 11, "DESCRIPTION": "1 Metal Bench", "PRORAGIS_ID": "3352", "YEAR_BUILT": null, "STREET_NUMBER": "900", "STATUS": "Open", "FACILITY_ID": "1003", "LWCF_PROTECTION": " ", "LONGITUDE": -97.74583481, "CREATED_BY": "hardya", "CITY_MUNICIPAL": "Austin", "PROTECTION_COMMENTS": null, "YEAR_OPEN": null, "STREET_NAME": "Guadalupe", "MANAGING_AGENCY_NAME": "City of Austin Parks and Recreation", "ASSET_MGMT_ID": 319.1003, "SIZE_UNITS": null, "MODIFIED_BY": "roosg", "LENGTH_UNITS": null, "ACCESSIBILITY_STATUS": "Accessible", "STATE": "TX", "FACILITY_TYPE": "Memorial", "ADDRESS": "900 Guadalupe St., Austin, Texas 78701", "RESERVATIONS": "No", "ZIP_CODE": "78701", "PARK_ID": "319", "COUNTY": "Travis", "PARD_ID_1": 319, "OTHER_PROTECTIONS": " ", "OBJECTID": 88, "FACILITYOWNER_TYPE": "Municipal", "STREET_TYPE": "St.", "CREATED_DATE": 1395065891000, "LATITUDE": 30.27278899, "WIDTH": null, "FACILITY_NAME": "Wooldridge Square: Gift of Austin Newcomers Club Memorial Bench", "MANAGINGAGENCY_TYPE": "Municipal", "FACILITY_OWNER_NAME": "City of Austin", "INDOOR_OUTDOOR": "Outdoor", "MODIFIED_DATE": 1427883586000, "FACILITY_SIZE": null}, "type": "Feature"}, {"geometry": {"coordinates": [-97.7455677552299, 30.2723436847366], "type": "Point"}, "id": 795, "properties": {"WIDTH_UNITS": null, "LENGTH": null, "FACILITY_CLASS": 16, "DESCRIPTION": "Trellis/Open Roof; No Benches", "PRORAGIS_ID": "2123", "YEAR_BUILT": null, "STREET_NUMBER": "900", "STATUS": "Open", "FACILITY_ID": "1601", "LWCF_PROTECTION": " ", "LONGITUDE": -97.74556776, "CREATED_BY": "hardya", "CITY_MUNICIPAL": "Austin", "PROTECTION_COMMENTS": null, "YEAR_OPEN": null, "STREET_NAME": "Guadalupe", "MANAGING_AGENCY_NAME": "City of Austin Parks and Recreation", "ASSET_MGMT_ID": 319.1601, "SIZE_UNITS": "Square Feet", "MODIFIED_BY": "hardya", "LENGTH_UNITS": null, "ACCESSIBILITY_STATUS": "Not Accessible", "STATE": "TX", "FACILITY_TYPE": "Gazebo", "ADDRESS": "900 Guadalupe St., Austin, Texas 78701", "RESERVATIONS": "No", "ZIP_CODE": "78701", "PARK_ID": "319", "COUNTY": "Travis", "PARD_ID_1": 319, "OTHER_PROTECTIONS": " ", "OBJECTID": 795, "FACILITYOWNER_TYPE": "Municipal", "STREET_TYPE": "St.", "CREATED_DATE": 1352366393000, "LATITUDE": 30.27234368, "WIDTH": null, "FACILITY_NAME": "Wooldridge Square Gazebo", "MANAGINGAGENCY_TYPE": "Municipal", "FACILITY_OWNER_NAME": "City of Austin Parks and Recreation", "INDOOR_OUTDOOR": "Outdoor", "MODIFIED_DATE": 1392381276000, "FACILITY_SIZE": 400}, "type": "Feature"}], "type": "FeatureCollection"}