{"features": [{"properties": {"PARD_ID_1": 328, "COUNTY": "Travis", "MODIFIED_BY": "hardya", "INDOOR_OUTDOOR": "Outdoor", "RESERVATIONS": "No", "PROTECTION_COMMENTS": null, "LWCF_PROTECTION": " ", "WIDTH": null, "FACILITY_OWNER_NAME": "City of Austin Parks and Recreation", "MANAGINGAGENCY_TYPE": "Municipal", "FACILITY_TYPE": "Visual Arts/Crafts", "OTHER_PROTECTIONS": " ", "FACILITY_NAME": "Manuel and Robert Donley Pocket Park: Archway Installation", "LENGTH_UNITS": null, "LATITUDE": 30.24987051, "ASSET_MGMT_ID": 328.1801, "STATUS": "Open", "YEAR_BUILT": null, "FACILITY_SIZE": null, "LONGITUDE": -97.72174724, "MODIFIED_DATE": 1408534071000, "CITY_MUNICIPAL": "Austin", "MANAGING_AGENCY_NAME": "City of Austin Parks and Recreation", "FACILITY_ID": "1801", "SIZE_UNITS": null, "DESCRIPTION": "Archway Installation", "ADDRESS": "2220 Riverview St., Austin, Texas 78702", "WIDTH_UNITS": null, "ACCESSIBILITY_STATUS": "Accessible", "STREET_NUMBER": "2220", "ZIP_CODE": "78702", "YEAR_OPEN": null, "PARK_ID": "328", "FACILITY_CLASS": 9, "CREATED_DATE": 1395222382000, "CREATED_BY": "hardya", "STREET_NAME": "Riverview", "STREET_TYPE": "St.", "PRORAGIS_ID": "3392", "OBJECTID": 1757, "STATE": "TX", "FACILITYOWNER_TYPE": "Municipal", "LENGTH": null}, "id": 1757, "geometry": {"coordinates": [-97.721747236054, 30.2498705140313], "type": "Point"}, "type": "Feature"}], "type": "FeatureCollection"}