{"type": "FeatureCollection", "features": [{"properties": {"ACCESSIBILITY_STATUS": "Accessible", "PARK_ID": "229", "STREET_NUMBER": "7000", "WIDTH": null, "LONGITUDE": -97.65140077, "YEAR_BUILT": null, "PARD_ID_1": 229, "CREATED_BY": "hardya", "FACILITY_TYPE": "Basketball", "OTHER_PROTECTIONS": " ", "ZIP_CODE": "78617", "MODIFIED_BY": "hardya", "PRORAGIS_ID": "1942", "PROTECTION_COMMENTS": null, "RESERVATIONS": "No", "ASSET_MGMT_ID": 229.301, "COUNTY": "Travis", "CREATED_DATE": 1304899200000, "STATE": "TX", "SIZE_UNITS": null, "MODIFIED_DATE": 1392380751000, "FACILITY_SIZE": null, "FACILITY_OWNER_NAME": "City of Austin Parks and Recreation", "INDOOR_OUTDOOR": "Outdoor", "FACILITY_NAME": "Stoney Ridge Neighborhood Park Basketball Court", "LWCF_PROTECTION": " ", "CITY_MUNICIPAL": "Austin LTD", "LATITUDE": 30.15793252, "WIDTH_UNITS": null, "FACILITY_ID": "301", "STREET_TYPE": "Blvd.", "STREET_NAME": "Moores Crossing", "LENGTH": null, "MANAGINGAGENCY_TYPE": "Municipal", "DESCRIPTION": "Full Court; Not Sheltered; 2 Goals", "OBJECTID": 379, "FACILITYOWNER_TYPE": "Municipal", "STATUS": "Open", "YEAR_OPEN": null, "MANAGING_AGENCY_NAME": "City of Austin Parks and Recreation", "ADDRESS": "7000 Moores Crossing Blvd., Austin, Texas 78617", "LENGTH_UNITS": null, "FACILITY_CLASS": 8}, "type": "Feature", "geometry": {"type": "Point", "coordinates": [-97.6514007734919, 30.1579325194959]}, "id": 379}, {"properties": {"ACCESSIBILITY_STATUS": "Not Accessible", "PARK_ID": "229", "STREET_NUMBER": "7000", "WIDTH": null, "LONGITUDE": -97.65208037, "YEAR_BUILT": null, "PARD_ID_1": 229, "CREATED_BY": "hardya", "FACILITY_TYPE": "Parking Lot", "OTHER_PROTECTIONS": " ", "ZIP_CODE": "78617", "MODIFIED_BY": "hardya", "PRORAGIS_ID": "1943", "PROTECTION_COMMENTS": null, "RESERVATIONS": "No", "ASSET_MGMT_ID": 229.2001, "COUNTY": "Travis", "CREATED_DATE": 1286323200000, "STATE": "TX", "SIZE_UNITS": null, "MODIFIED_DATE": 1392380753000, "FACILITY_SIZE": null, "FACILITY_OWNER_NAME": "City of Austin Parks and Recreation", "INDOOR_OUTDOOR": "Outdoor", "FACILITY_NAME": "Stoney Ridge Neighborhood Park Parking Lot", "LWCF_PROTECTION": " ", "CITY_MUNICIPAL": "Austin LTD", "LATITUDE": 30.1584085, "WIDTH_UNITS": null, "FACILITY_ID": "2001", "STREET_TYPE": "Blvd.", "STREET_NAME": "Moores Crossing", "LENGTH": null, "MANAGINGAGENCY_TYPE": "Municipal", "DESCRIPTION": "Concrete; 7 Regular Spaces/ 0 ADA Spaces", "OBJECTID": 380, "FACILITYOWNER_TYPE": "Municipal", "STATUS": "Open", "YEAR_OPEN": null, "MANAGING_AGENCY_NAME": "City of Austin Parks and Recreation", "ADDRESS": "7000 Moores Crossing Blvd., Austin, Texas 78617", "LENGTH_UNITS": null, "FACILITY_CLASS": 20}, "type": "Feature", "geometry": {"type": "Point", "coordinates": [-97.6520803710388, 30.1584085020557]}, "id": 380}, {"properties": {"ACCESSIBILITY_STATUS": "Not Accessible", "PARK_ID": "229", "STREET_NUMBER": "7000", "WIDTH": null, "LONGITUDE": -97.65177212, "YEAR_BUILT": null, "PARD_ID_1": 229, "CREATED_BY": "hardya", "FACILITY_TYPE": "Playground", "OTHER_PROTECTIONS": " ", "ZIP_CODE": "78617", "MODIFIED_BY": "hardya", "PRORAGIS_ID": "2305", "PROTECTION_COMMENTS": null, "RESERVATIONS": "No", "ASSET_MGMT_ID": 229.1401, "COUNTY": "Travis", "CREATED_DATE": 1359331200000, "STATE": "TX", "SIZE_UNITS": null, "MODIFIED_DATE": 1392395572000, "FACILITY_SIZE": null, "FACILITY_OWNER_NAME": "City of Austin Parks and Recreation", "INDOOR_OUTDOOR": "Outdoor", "FACILITY_NAME": "Stoney Ridge Neighborhood Park Playground", "LWCF_PROTECTION": " ", "CITY_MUNICIPAL": "Austin LTD", "LATITUDE": 30.15815771, "WIDTH_UNITS": null, "FACILITY_ID": "1401", "STREET_TYPE": "Blvd.", "STREET_NAME": "Moores Crossing", "LENGTH": null, "MANAGINGAGENCY_TYPE": "Municipal", "DESCRIPTION": "SRM;1 Youth Playscape(Roof)", "OBJECTID": 1045, "FACILITYOWNER_TYPE": "Municipal", "STATUS": "Open", "YEAR_OPEN": null, "MANAGING_AGENCY_NAME": "City of Austin Parks and Recreation", "ADDRESS": "7000 Moores Crossing Blvd., Austin, Texas 78617", "LENGTH_UNITS": null, "FACILITY_CLASS": 3}, "type": "Feature", "geometry": {"type": "Point", "coordinates": [-97.6517721199982, 30.1581577118731]}, "id": 1045}]}