{"features": [{"geometry": {"coordinates": [-97.721747236054, 30.2498705140313], "type": "Point"}, "id": 1757, "properties": {"WIDTH_UNITS": null, "LENGTH": null, "FACILITY_CLASS": 9, "DESCRIPTION": "Archway Installation", "PRORAGIS_ID": "3392", "YEAR_BUILT": null, "STREET_NUMBER": "2220", "STATUS": "Open", "FACILITY_ID": "1801", "LWCF_PROTECTION": " ", "LONGITUDE": -97.72174724, "CREATED_BY": "hardya", "CITY_MUNICIPAL": "Austin", "PROTECTION_COMMENTS": null, "YEAR_OPEN": null, "STREET_NAME": "Riverview", "MANAGING_AGENCY_NAME": "City of Austin Parks and Recreation", "ASSET_MGMT_ID": 328.1801, "SIZE_UNITS": null, "MODIFIED_BY": "hardya", "LENGTH_UNITS": null, "ACCESSIBILITY_STATUS": "Accessible", "STATE": "TX", "FACILITY_TYPE": "Visual Arts/Crafts", "ADDRESS": "2220 Riverview St., Austin, Texas 78702", "RESERVATIONS": "No", "ZIP_CODE": "78702", "PARK_ID": "328", "COUNTY": "Travis", "PARD_ID_1": 328, "OTHER_PROTECTIONS": " ", "OBJECTID": 1757, "FACILITYOWNER_TYPE": "Municipal", "STREET_TYPE": "St.", "CREATED_DATE": 1395222382000, "LATITUDE": 30.24987051, "WIDTH": null, "FACILITY_NAME": "Manuel and Robert Donley Pocket Park: Archway Installation", "MANAGINGAGENCY_TYPE": "Municipal", "FACILITY_OWNER_NAME": "City of Austin Parks and Recreation", "INDOOR_OUTDOOR": "Outdoor", "MODIFIED_DATE": 1408534071000, "FACILITY_SIZE": null}, "type": "Feature"}], "type": "FeatureCollection"}