{"features": [{"properties": {"PARD_ID_1": 117, "COUNTY": "Travis", "MODIFIED_BY": "hardya", "INDOOR_OUTDOOR": "Outdoor", "RESERVATIONS": "No", "PROTECTION_COMMENTS": null, "LWCF_PROTECTION": " ", "WIDTH": null, "FACILITY_OWNER_NAME": "City of Austin Parks and Recreation", "MANAGINGAGENCY_TYPE": "Municipal", "FACILITY_TYPE": "Basketball", "OTHER_PROTECTIONS": " ", "FACILITY_NAME": "Battle Bend Neighborhood Park Basketball Court", "LENGTH_UNITS": null, "LATITUDE": 30.2138843, "ASSET_MGMT_ID": 117.301, "STATUS": "Open", "YEAR_BUILT": null, "FACILITY_SIZE": null, "LONGITUDE": -97.76751849, "MODIFIED_DATE": 1392289054000, "CITY_MUNICIPAL": "Austin", "MANAGING_AGENCY_NAME": "City of Austin Parks and Recreation", "FACILITY_ID": "301", "SIZE_UNITS": null, "DESCRIPTION": "Full Court; Not Sheltered; 2 Goals", "ADDRESS": "121 Sheraton Ave., Austin, Texas 78745", "WIDTH_UNITS": null, "ACCESSIBILITY_STATUS": "Not Accessible", "STREET_NUMBER": "121", "ZIP_CODE": "78745", "YEAR_OPEN": null, "PARK_ID": "117", "FACILITY_CLASS": 8, "CREATED_DATE": 1021507200000, "CREATED_BY": "<Null>", "STREET_NAME": "Sheraton ", "STREET_TYPE": "Ave.", "PRORAGIS_ID": "184", "OBJECTID": 1622, "STATE": "TX", "FACILITYOWNER_TYPE": "Municipal", "LENGTH": null}, "id": 1622, "geometry": {"coordinates": [-97.7675184856076, 30.2138842950996], "type": "Point"}, "type": "Feature"}, {"properties": {"PARD_ID_1": 117, "COUNTY": "Travis", "MODIFIED_BY": "hardya", "INDOOR_OUTDOOR": "Outdoor", "RESERVATIONS": "No", "PROTECTION_COMMENTS": null, "LWCF_PROTECTION": " ", "WIDTH": null, "FACILITY_OWNER_NAME": "City of Austin Parks and Recreation", "MANAGINGAGENCY_TYPE": "Municipal", "FACILITY_TYPE": "Gazebo", "OTHER_PROTECTIONS": " ", "FACILITY_NAME": "Battle Bend Neighborhood Park Gazebo", "LENGTH_UNITS": null, "LATITUDE": 30.21418474, "ASSET_MGMT_ID": 117.1601, "STATUS": "Open", "YEAR_BUILT": null, "FACILITY_SIZE": 400, "LONGITUDE": -97.76768635, "MODIFIED_DATE": 1392289056000, "CITY_MUNICIPAL": "Austin", "MANAGING_AGENCY_NAME": "City of Austin Parks and Recreation", "FACILITY_ID": "1601", "SIZE_UNITS": "Square Feet", "DESCRIPTION": "Covered Roof; 3 Benches", "ADDRESS": "121 Sheraton Ave., Austin, Texas 78745", "WIDTH_UNITS": null, "ACCESSIBILITY_STATUS": "Not Accessible", "STREET_NUMBER": "121", "ZIP_CODE": "78745", "YEAR_OPEN": null, "PARK_ID": "117", "FACILITY_CLASS": 16, "CREATED_DATE": 1352366398000, "CREATED_BY": "hardya", "STREET_NAME": "Sheraton ", "STREET_TYPE": "Ave.", "PRORAGIS_ID": "185", "OBJECTID": 1623, "STATE": "TX", "FACILITYOWNER_TYPE": "Municipal", "LENGTH": null}, "id": 1623, "geometry": {"coordinates": [-97.7676863454256, 30.214184735946], "type": "Point"}, "type": "Feature"}, {"properties": {"PARD_ID_1": 117, "COUNTY": "Travis", "MODIFIED_BY": "hardya", "INDOOR_OUTDOOR": "Outdoor", "RESERVATIONS": "No", "PROTECTION_COMMENTS": null, "LWCF_PROTECTION": " ", "WIDTH": null, "FACILITY_OWNER_NAME": "City of Austin Parks and Recreation", "MANAGINGAGENCY_TYPE": "Municipal", "FACILITY_TYPE": "Playground", "OTHER_PROTECTIONS": " ", "FACILITY_NAME": "Battle Bend Neighborhood Park Playground", "LENGTH_UNITS": null, "LATITUDE": 30.21416728, "ASSET_MGMT_ID": 117.1401, "STATUS": "Open", "YEAR_BUILT": null, "FACILITY_SIZE": null, "LONGITUDE": -97.76791433, "MODIFIED_DATE": 1392289058000, "CITY_MUNICIPAL": "Austin", "MANAGING_AGENCY_NAME": "City of Austin Parks and Recreation", "FACILITY_ID": "1401", "SIZE_UNITS": null, "DESCRIPTION": "Peagravel/PIP;1 Tot Playscape;1 Youth Playscape;1 Tot Swing(1 Bay, 2 Buckets)", "ADDRESS": "121 Sheraton Ave., Austin, Texas 78745", "WIDTH_UNITS": null, "ACCESSIBILITY_STATUS": "Accessible", "STREET_NUMBER": "121", "ZIP_CODE": "78745", "YEAR_OPEN": null, "PARK_ID": "117", "FACILITY_CLASS": 3, "CREATED_DATE": 1359504000000, "CREATED_BY": "hardya", "STREET_NAME": "Sheraton ", "STREET_TYPE": "Ave.", "PRORAGIS_ID": "186", "OBJECTID": 1624, "STATE": "TX", "FACILITYOWNER_TYPE": "Municipal", "LENGTH": null}, "id": 1624, "geometry": {"coordinates": [-97.7679143278681, 30.214167284523], "type": "Point"}, "type": "Feature"}], "type": "FeatureCollection"}