{"type": "FeatureCollection", "features": [{"properties": {"ACCESSIBILITY_STATUS": "Accessible", "PARK_ID": "319", "STREET_NUMBER": "900", "WIDTH": null, "LONGITUDE": -97.74583481, "YEAR_BUILT": null, "PARD_ID_1": 319, "CREATED_BY": "hardya", "FACILITY_TYPE": "Memorial", "OTHER_PROTECTIONS": " ", "ZIP_CODE": "78701", "MODIFIED_BY": "roosg", "PRORAGIS_ID": "3352", "PROTECTION_COMMENTS": null, "RESERVATIONS": "No", "ASSET_MGMT_ID": 319.1003, "COUNTY": "Travis", "CREATED_DATE": 1395065891000, "STATE": "TX", "SIZE_UNITS": null, "MODIFIED_DATE": 1427883586000, "FACILITY_SIZE": null, "FACILITY_OWNER_NAME": "City of Austin", "INDOOR_OUTDOOR": "Outdoor", "FACILITY_NAME": "Wooldridge Square: Gift of Austin Newcomers Club Memorial Bench", "LWCF_PROTECTION": " ", "CITY_MUNICIPAL": "Austin", "LATITUDE": 30.27278899, "WIDTH_UNITS": null, "FACILITY_ID": "1003", "STREET_TYPE": "St.", "STREET_NAME": "Guadalupe", "LENGTH": null, "MANAGINGAGENCY_TYPE": "Municipal", "DESCRIPTION": "1 Metal Bench", "OBJECTID": 88, "FACILITYOWNER_TYPE": "Municipal", "STATUS": "Open", "YEAR_OPEN": null, "MANAGING_AGENCY_NAME": "City of Austin Parks and Recreation", "ADDRESS": "900 Guadalupe St., Austin, Texas 78701", "LENGTH_UNITS": null, "FACILITY_CLASS": 11}, "type": "Feature", "geometry": {"type": "Point", "coordinates": [-97.7458348054309, 30.2727889868446]}, "id": 88}, {"properties": {"ACCESSIBILITY_STATUS": "Not Accessible", "PARK_ID": "319", "STREET_NUMBER": "900", "WIDTH": null, "LONGITUDE": -97.74556776, "YEAR_BUILT": null, "PARD_ID_1": 319, "CREATED_BY": "hardya", "FACILITY_TYPE": "Gazebo", "OTHER_PROTECTIONS": " ", "ZIP_CODE": "78701", "MODIFIED_BY": "hardya", "PRORAGIS_ID": "2123", "PROTECTION_COMMENTS": null, "RESERVATIONS": "No", "ASSET_MGMT_ID": 319.1601, "COUNTY": "Travis", "CREATED_DATE": 1352366393000, "STATE": "TX", "SIZE_UNITS": "Square Feet", "MODIFIED_DATE": 1392381276000, "FACILITY_SIZE": 400, "FACILITY_OWNER_NAME": "City of Austin Parks and Recreation", "INDOOR_OUTDOOR": "Outdoor", "FACILITY_NAME": "Wooldridge Square Gazebo", "LWCF_PROTECTION": " ", "CITY_MUNICIPAL": "Austin", "LATITUDE": 30.27234368, "WIDTH_UNITS": null, "FACILITY_ID": "1601", "STREET_TYPE": "St.", "STREET_NAME": "Guadalupe", "LENGTH": null, "MANAGINGAGENCY_TYPE": "Municipal", "DESCRIPTION": "Trellis/Open Roof; No Benches", "OBJECTID": 795, "FACILITYOWNER_TYPE": "Municipal", "STATUS": "Open", "YEAR_OPEN": null, "MANAGING_AGENCY_NAME": "City of Austin Parks and Recreation", "ADDRESS": "900 Guadalupe St., Austin, Texas 78701", "LENGTH_UNITS": null, "FACILITY_CLASS": 16}, "type": "Feature", "geometry": {"type": "Point", "coordinates": [-97.7455677552299, 30.2723436847366]}, "id": 795}]}