{"type": "FeatureCollection", "features": [{"properties": {"ACCESSIBILITY_STATUS": "Accessible", "PARK_ID": "246", "STREET_NUMBER": "8601", "WIDTH": null, "LONGITUDE": -97.83210976, "YEAR_BUILT": null, "PARD_ID_1": 246, "CREATED_BY": "hardya", "FACILITY_TYPE": "Playground", "OTHER_PROTECTIONS": " ", "ZIP_CODE": "78745", "MODIFIED_BY": "hardya", "PRORAGIS_ID": "1571", "PROTECTION_COMMENTS": null, "RESERVATIONS": "No", "ASSET_MGMT_ID": 246.1401, "COUNTY": "Travis", "CREATED_DATE": 1359504000000, "STATE": "TX", "SIZE_UNITS": null, "MODIFIED_DATE": 1392379649000, "FACILITY_SIZE": null, "FACILITY_OWNER_NAME": "City of Austin Parks and Recreation", "INDOOR_OUTDOOR": "Outdoor", "FACILITY_NAME": "Piney Bend Neighborhood Park Playground", "LWCF_PROTECTION": " ", "CITY_MUNICIPAL": "Austin", "LATITUDE": 30.19389549, "WIDTH_UNITS": null, "FACILITY_ID": "1401", "STREET_TYPE": "Bnd.", "STREET_NAME": "Piney Creek", "LENGTH": null, "MANAGINGAGENCY_TYPE": "Municipal", "DESCRIPTION": "EWF;1 Youth Playscape(Roof);1 Tot/Youth Swing(3 Bays, 2 Buckets, 4 Belts)", "OBJECTID": 227, "FACILITYOWNER_TYPE": "Municipal", "STATUS": "Open", "YEAR_OPEN": null, "MANAGING_AGENCY_NAME": "City of Austin Parks and Recreation", "ADDRESS": "8601 Piney Creek Bnd., Austin, Texas 78745", "LENGTH_UNITS": null, "FACILITY_CLASS": 3}, "type": "Feature", "geometry": {"type": "Point", "coordinates": [-97.8321097561376, 30.1938954854767]}, "id": 227}]}