{"type": "FeatureCollection", "features": [{"properties": {"ACCESSIBILITY_STATUS": "Not Accessible", "PARK_ID": "224", "STREET_NUMBER": "2806", "WIDTH": null, "LONGITUDE": -97.70359989, "YEAR_BUILT": null, "PARD_ID_1": 224, "CREATED_BY": "<Null>", "FACILITY_TYPE": "Basketball", "OTHER_PROTECTIONS": " ", "ZIP_CODE": "78702", "MODIFIED_BY": "hardya", "PRORAGIS_ID": "1452", "PROTECTION_COMMENTS": null, "RESERVATIONS": "No", "ASSET_MGMT_ID": 224.301, "COUNTY": "Travis", "CREATED_DATE": 1026950400000, "STATE": "TX", "SIZE_UNITS": null, "MODIFIED_DATE": 1392379250000, "FACILITY_SIZE": null, "FACILITY_OWNER_NAME": "Austin Independent School District", "INDOOR_OUTDOOR": "Outdoor", "FACILITY_NAME": "Oak Springs School Park Basketball Court", "LWCF_PROTECTION": " ", "CITY_MUNICIPAL": "Austin", "LATITUDE": 30.27169187, "WIDTH_UNITS": null, "FACILITY_ID": "301", "STREET_TYPE": "Ave.", "STREET_NAME": "Goodwin", "LENGTH": null, "MANAGINGAGENCY_TYPE": "Municipal", "DESCRIPTION": "Full Court; Sheltered with ShadeCloth; 2 Goals", "OBJECTID": 16, "FACILITYOWNER_TYPE": "School", "STATUS": "Open_Restricted", "YEAR_OPEN": null, "MANAGING_AGENCY_NAME": "City of Austin Parks and Recreation", "ADDRESS": "2806 Goodwin Ave., Austin, Texas 78702", "LENGTH_UNITS": null, "FACILITY_CLASS": 8}, "type": "Feature", "geometry": {"type": "Point", "coordinates": [-97.7035998884451, 30.2716918712024]}, "id": 16}, {"properties": {"ACCESSIBILITY_STATUS": "Accessible", "PARK_ID": "224", "STREET_NUMBER": "2806", "WIDTH": null, "LONGITUDE": -97.70445219, "YEAR_BUILT": null, "PARD_ID_1": 224, "CREATED_BY": "<Null>", "FACILITY_TYPE": "Parking Lot", "OTHER_PROTECTIONS": " ", "ZIP_CODE": "78702", "MODIFIED_BY": "hardya", "PRORAGIS_ID": "1454", "PROTECTION_COMMENTS": null, "RESERVATIONS": "No", "ASSET_MGMT_ID": 224.2001, "COUNTY": "Travis", "CREATED_DATE": 1026950400000, "STATE": "TX", "SIZE_UNITS": null, "MODIFIED_DATE": 1392379254000, "FACILITY_SIZE": null, "FACILITY_OWNER_NAME": "Austin Independent School District", "INDOOR_OUTDOOR": "Outdoor", "FACILITY_NAME": "Oak Springs School Park Parking Lot", "LWCF_PROTECTION": " ", "CITY_MUNICIPAL": "Austin", "LATITUDE": 30.2711371, "WIDTH_UNITS": null, "FACILITY_ID": "2001", "STREET_TYPE": "Ave.", "STREET_NAME": "Goodwin", "LENGTH": null, "MANAGINGAGENCY_TYPE": "School", "DESCRIPTION": "Concrete; 20 Regular Spaces/ 2 ADA Spaces/ School Parking", "OBJECTID": 17, "FACILITYOWNER_TYPE": "School", "STATUS": "Open_Restricted", "YEAR_OPEN": null, "MANAGING_AGENCY_NAME": "Austin Independent School District", "ADDRESS": "2806 Goodwin Ave., Austin, Texas 78702", "LENGTH_UNITS": null, "FACILITY_CLASS": 20}, "type": "Feature", "geometry": {"type": "Point", "coordinates": [-97.7044521860091, 30.2711371048757]}, "id": 17}, {"properties": {"ACCESSIBILITY_STATUS": "Not Accessible", "PARK_ID": "224", "STREET_NUMBER": "2806", "WIDTH": null, "LONGITUDE": -97.70316186, "YEAR_BUILT": null, "PARD_ID_1": 224, "CREATED_BY": "hardya", "FACILITY_TYPE": "Mixed Use Field", "OTHER_PROTECTIONS": " ", "ZIP_CODE": "78702", "MODIFIED_BY": "hardya", "PRORAGIS_ID": "1453", "PROTECTION_COMMENTS": null, "RESERVATIONS": "Yes", "ASSET_MGMT_ID": 224.1901, "COUNTY": "Travis", "CREATED_DATE": 1199145600000, "STATE": "TX", "SIZE_UNITS": null, "MODIFIED_DATE": 1398089599000, "FACILITY_SIZE": null, "FACILITY_OWNER_NAME": "Austin Independent School District", "INDOOR_OUTDOOR": "Outdoor", "FACILITY_NAME": "Oak Springs School Park Mixed Use Field", "LWCF_PROTECTION": " ", "CITY_MUNICIPAL": "Austin", "LATITUDE": 30.27211691, "WIDTH_UNITS": null, "FACILITY_ID": "1901", "STREET_TYPE": "Ave.", "STREET_NAME": "Goodwin", "LENGTH": null, "MANAGINGAGENCY_TYPE": "Municipal", "DESCRIPTION": "No Backstop; No Goals; No Lights; No Stands; No Scoreboard", "OBJECTID": 1416, "FACILITYOWNER_TYPE": "School", "STATUS": "Open_Restricted", "YEAR_OPEN": null, "MANAGING_AGENCY_NAME": "City of Austin Parks and Recreation", "ADDRESS": "2806 Goodwin Ave., Austin, Texas 78702", "LENGTH_UNITS": null, "FACILITY_CLASS": 10}, "type": "Feature", "geometry": {"type": "Point", "coordinates": [-97.7031618637322, 30.272116905368]}, "id": 1416}]}